multi-cycle/src/core/ControlUnit.v
module controlUnit(
    input clk,
    input reset,
    input [31:0] instr,
    output logic pcUpdate,
    output logic adrSrc,
    output logic memWrite,
    output logic IRWrite,
    output logic regWrite,
    output logic [2:0] immSrc,
    output logic ALUSrcA,
    output logic [1:0] ALUSrcB,
    output logic invertOp,
    output logic [2:0] ALUCtrl,
    output logic [1:0] resSrc
);
    
    wire [6:0] funct7;
    wire [2:0] funct3; 
    wire [6:0] opcode;
    wire invertOp_t;

    assign funct7 = instr[31:25];
    assign funct3 = instr[14:12];
    assign opcode = instr[6:0];
    assign invertOp_t = funct7[5];

    
    localparam memFetch = 3'd0;
    localparam fetch = 3'd1;
    localparam decode = 3'd2;
    localparam execute_R = 3'd3;
    localparam writeBack_ALU = 3'd4;
    localparam execute_I = 3'd5;
    localparam memRead = 3'd6;
    localparam writeBack_mem = 3'd7;

    logic [2:0] currentState, nextState;

    //MAIN FSM
    //NEXT STATE LOGIC
    always_comb begin
        nextState = currentState; //Default Case
        case(currentState)
            memFetch: nextState = fetch;
            fetch: nextState = decode;
            decode: begin
                case(opcode)
                    7'b0110011: nextState = execute_R;
                    7'b0010011: nextState = execute_I;
                    7'b0000011: nextState = memRead;
                endcase
            end
            execute_R: nextState = writeBack_ALU;
            execute_I: nextState = writeBack_ALU;
            memRead: nextState = writeBack_mem;
            writeBack_mem: nextState = memFetch;
            writeBack_ALU: nextState = memFetch;
        endcase
    end

    //FSM REGISTER
    always_ff @(posedge clk) begin
        if(reset)
            currentState <= memFetch;
        else
            currentState <= nextState;
    end

    //OUTPUT LOGIC
    always_comb begin
        pcUpdate = 0;
        adrSrc = 0;
        memWrite = 0;
        IRWrite = 0;
        regWrite = 0;
        immSrc = 3'd0;
        ALUSrcA = 0;
        ALUSrcB = 2'd0;
        invertOp = 0;
        resSrc = 2'd0;
        case(currentState)
            memFetch: begin
                pcUpdate = 1;
                ALUSrcA = 0;        //Setting ALU to calculate PC+4 here to support correct PC update after reset
                ALUSrcB = 2'd1;
                resSrc = 2'd0;
                IRWrite = 1;
            end
            fetch: begin
                //IRWrite = 1;
            end
            decode: begin
                ALUSrcA = 1;
                ALUSrcB = 2'd2;
                immSrc = 3'd0;
                resSrc = 2'd1;
                adrSrc = 1;
            end
            memRead: begin
                resSrc = 2'd0;
                adrSrc = 1;
            end
            writeBack_mem: begin
                resSrc = 2'd2;
                regWrite = 1;
                ALUSrcA = 0;
                ALUSrcB = 2'd1;
            end
            execute_R: begin
                ALUSrcA = 1;
                ALUSrcB = 2'd0;
                invertOp = invertOp_t;
            end
            execute_I: begin
                ALUSrcA = 1;
                ALUSrcB = 2'd2;
                immSrc = 3'd0;
                if(funct3 == 3'b101)
                    invertOp = invertOp_t;
            end
            writeBack_ALU: begin
                resSrc = 2'd0;
                regWrite = 1;
                ALUSrcA = 0;
                ALUSrcB = 2'd1;
            end
        endcase
    end

    //ALU DECODER
    always_comb begin
        ALUCtrl = 3'd0;
        case(currentState)
            memFetch: ALUCtrl = 3'b000;
            decode: ALUCtrl = 3'b000;
            execute_R: ALUCtrl = funct3;
            execute_I: ALUCtrl = funct3;
            writeBack_mem: ALUCtrl = 3'b000;
            writeBack_ALU: ALUCtrl = 3'b000;
        endcase
    end
endmodule

multi-cycle/src/blocks/ImmediateGenerator.v
module immediateGenerator(input [31:7] instr, input [2:0] immSrc, output reg [31:0] extendedImm);

    always @(*) begin
        extendedImm = 0;
        case(immSrc)
            3'b000: extendedImm = {{20{instr[31]}}, instr[31:20]}; //I Type
            3'b001: extendedImm = {{20{instr[31]}}, instr[31:25], instr[11:7]}; //S Type
            3'b010: extendedImm = {{20{instr[31]}}, instr[7], instr[30:25], instr[11:8], 1'b0}; //B Type
            3'b011: extendedImm = {instr[31:12], 12'b0}; //U type
            3'b100: extendedImm = {{11{instr[31]}}, instr[31], instr[20], instr[19:12], instr[30:21], 1'b0}; //J Type
            default: extendedImm = 32'b0;
        endcase
        //$display("%0d", extendedImm);
    end

endmodule

multi-cycle/src/blocks/ALU.v
module ALU(
    input [31:0] A,
    input [31:0] B,
    input invertOp,
    input [2:0] ALUCtrl,
    output reg [31:0] ALURes,
    output zero,
    output overflow
);
    wire [31:0] BEff;
    wire [31:0] resSub;
    assign BEff = (invertOp)? (~B + 1) : B;
    assign resSub = A-B;
    assign overflow = (A[31] != B[31]) && (resSub[31] != A[31]);
    assign zero = (resSub == 0);
    always @(*) begin
      case(ALUCtrl)
        3'b000: ALURes = A+BEff; //ADD/Sub
        3'b001: ALURes = A << B[4:0]; //SLL
        3'b010: ALURes = {31'b0, $signed(A) < $signed(B)}; //SLT
        3'b011: ALURes = A < B; //SLTU
        3'b100: ALURes = A ^ B; //XOR
        3'b101: ALURes = (!invertOp)? (A >> B[4:0]) : ($signed(A) >> B[4:0]); //SRL/SRA
        3'b110: ALURes = A | B;
        3'b111: ALURes = A & B;
      endcase
    end

endmodule

multi-cycle/src/utils/nMux.v
module nMux #(
    parameter N = 4
)(
    input [31:0] in [N-1:0],
    input [$clog2(N)-1:0] sel,
    output [31:0] out
);
    assign out = in[sel];
endmodule

multi-cycle/src/utils/Reg32.v
module reg32(
    input clk,
    input reset,
    input [31:0] in,
    output reg [31:0] out
);

    always @(posedge clk) begin
        if(reset)
            out <= 32'b0;
        else
            out <= in;
    end
endmodule

module enReg32(
    input clk,
    input reset,
    input enable,
    input [31:0] in,
    output reg [31:0] out
);
    always @(posedge clk) begin
        if(reset)
            out <= 32'b0;
        else if(enable)
            out <= in;
    end
endmodule

multi-cycle/src/blocks/Memory.v
module memory(
    input clk,
    input memWrite,
    input [31:0] A1,
    input [31:0] WD,
    output reg [31:0] RD
);

    reg [31:0] mem [0:2047];

    //Synchronous Memory
    always @(posedge clk) begin
        RD <= mem[A1[12:2]];
        if(memWrite)
            mem[A1[12:2]] <= WD;
    end

    initial begin
        $readmemh("sim/program.hex", mem);
    end
    initial begin
        mem[32'h100 >> 2] = 32'hDEADBEEF;
        mem[32'h104 >> 2] = 32'hCAFEBABE;
        mem[32'h108 >> 2] = 32'h12345678;
        mem[32'h0FC >> 2] = 32'hAABBCCDD;
        mem[32'h200 >> 2] = 32'h11223344;
        mem[32'h204 >> 2] = 32'h55667788;
        mem[32'h208 >> 2] = 32'h99AABBCC;
    end
endmodule

multi-cycle/src/blocks/RegisterFile.v
module registerFile(
    input clk,
    input reset,
    input regWrite,
    input [4:0] A1,
    input [4:0] A2,
    input [4:0] A3,
    input [31:0] WD,
    output [31:0] R1,
    output [31:0] R2
);

    reg [31:0] rFile [31:0];
    assign R1 = (A1 == 0)? 32'b0:rFile[A1];
    assign R2 = (A2 == 0)? 32'b0:rFile[A2];

    always @(posedge clk) begin
        if(reset) begin
            rFile[0] = 32'd0;
        end
        else if(regWrite && (A3 != 0)) begin
            rFile[A3] <= WD;
            $display("Write: x%0d = %0d (0x%h) time=%0t", A3, WD, WD, $time);
        end
    end

endmodule

multi-cycle/src/blocks/ProgramCounter.v
module programCounter(
    input clk,
    input reset,
    input pcUpdate,
    input [31:0] nextPC,
    output reg [31:0] currPC
);
    always @(posedge clk) begin
        if(reset)
            currPC <= 32'b0;
        else if(pcUpdate)
            currPC <= nextPC;
    end
endmodule

multi-cycle/src/core/datapath.v
module dataPath(
    input clk,
    input reset,
    input pcUpdate,
    input adrSrc,
    input memWrite,
    input IRWrite,
    input regWrite,
    input [2:0] immSrc,
    input ALUSrcA,
    input [1:0] ALUSrcB,
    input invertOp,
    input [2:0] ALUCtrl,
    input [1:0] resSrc,
    output [31:0] instOut
);
    wire [31:0] currPC;
    wire [31:0] adrMuxIn [1:0];
    wire [31:0] memIn;
    wire [31:0] memRead;
    wire [31:0] instr;
    wire [31:0] reg1, reg2; // Register File Outputs
    wire [31:0] ALUSrcAMuxIn [1:0];
    wire [31:0] ALUSrcBMuxIn [3:0];
    wire [31:0] ALUA, ALUB;
    wire [31:0] ALURes;
    wire [31:0] resMuxIn [3:0];
    wire [31:0] result;
    wire zero, overflow;


    //Architectural State Elements
    programCounter PC(.clk(clk), .reset(reset), .pcUpdate(pcUpdate), .nextPC(result), .currPC(currPC));
    registerFile regFile(.clk(clk), .reset(reset), .regWrite(regWrite), .A1(instr[19:15]), .A2(instr[24:20]), .A3(instr[11:7]), .WD(result), .R1(reg1), .R2(reg2));
    memory mem(.clk(clk), .memWrite(memWrite), .A1(memIn), .WD(), .RD(memRead));
    
    //Non Architectural State Elements
    enReg32 IRReg(.clk(clk), .reset(reset), .enable(IRWrite), .in(memRead), .out(instr));
    reg32 A(.clk(clk), .reset(reset), .in(reg1), .out(ALUSrcAMuxIn[1]));
    reg32 B(.clk(clk), .reset(reset), .in(reg2), .out(ALUSrcBMuxIn[0]));
    reg32 aluOut(.clk(clk), .reset(reset), .in(ALURes), .out(resMuxIn[0]));

    //Combinational Elements
    assign adrMuxIn[0] = currPC;
    assign adrMuxIn[1] = result;
    nMux #(.N(2)) adrMux(.in(adrMuxIn), .sel(adrSrc), .out(memIn));

    assign ALUSrcAMuxIn[0] = currPC;
    assign ALUSrcBMuxIn[1] = 32'd4;
    assign ALUSrcBMuxIn[3] = 32'd0;
    nMux #(.N(2)) ALUSrcAMux(.in(ALUSrcAMuxIn), .sel(ALUSrcA), .out(ALUA));
    nMux #(.N(4)) ALUSrcBMux(.in(ALUSrcBMuxIn), .sel(ALUSrcB), .out(ALUB));
    
    assign resMuxIn[1] = ALURes;
    assign resMuxIn[2] = memRead;
    assign resMuxIn[3] = 32'd0;
    nMux #(.N(4)) resMux(.in(resMuxIn), .sel(resSrc), .out(result));

    ALU alu(.A(ALUA), .B(ALUB), .invertOp(invertOp), .ALUCtrl(ALUCtrl), .ALURes(ALURes), .zero(zero), .overflow(overflow));
    immediateGenerator immGen(.instr(instr[31:7]), .immSrc(immSrc), .extendedImm(ALUSrcBMuxIn[2]));

    assign instOut = instr;
endmodule

multi-cycle/src/core/cpu.v
module CPU(
    input clk,
    input reset
);
    //Control Wires
    wire pcUpdate;
    wire adrSrc;
    wire memWrite;
    wire IRWrite;
    wire regWrite;
    wire [2:0] immSrc;
    wire ALUSrcA;
    wire [1:0] ALUSrcB;
    wire invertOp;
    wire [2:0] ALUCtrl;
    wire [1:0] resSrc;
    wire [31:0] instr;

    dataPath DP(
        .clk(clk),
        .reset(reset),
        .pcUpdate(pcUpdate),
        .adrSrc(adrSrc),
        .memWrite(memWrite),
        .IRWrite(IRWrite),
        .regWrite(regWrite),
        .immSrc(immSrc),
        .ALUSrcA(ALUSrcA),
        .ALUSrcB(ALUSrcB),
        .invertOp(invertOp),
        .ALUCtrl(ALUCtrl),
        .resSrc(resSrc),
        .instOut(instr)
    );

    controlUnit CP(
        .clk(clk),
        .reset(reset),
        .instr(instr),
        .pcUpdate(pcUpdate),
        .adrSrc(adrSrc),
        .memWrite(memWrite),
        .IRWrite(IRWrite),
        .regWrite(regWrite),
        .immSrc(immSrc),
        .ALUSrcA(ALUSrcA),
        .ALUSrcB(ALUSrcB),
        .invertOp(invertOp),
        .ALUCtrl(ALUCtrl),
        .resSrc(resSrc)
    );
endmodule

multi-cycle/sim/cpu_tb.v
`timescale 1ns/1ps

module cpu_tb();
    reg clk;
    reg reset;

    initial begin
        clk = 0;
        forever #5 clk = ~clk;
    end

    CPU DUT(.clk(clk), .reset(reset));
    initial begin
        $dumpfile("wave.vcd");
        $dumpvars(0, cpu_tb);
        reset = 1; #20
        reset = 0; #1000
        $finish;
    end
endmodule

multi-cycle/wave.vcd
$date
	Sun Jun  7 06:13:44 2026
$end
$version
	Icarus Verilog
$end
$timescale
	1ps
$end
$scope module cpu_tb $end
$var reg 1 ! clk $end
$var reg 1 " reset $end
$scope module DUT $end
$var wire 1 ! clk $end
$var wire 1 " reset $end
$var wire 2 # resSrc [1:0] $end
$var wire 1 $ regWrite $end
$var wire 1 % pcUpdate $end
$var wire 1 & memWrite $end
$var wire 1 ' invertOp $end
$var wire 32 ( instr [31:0] $end
$var wire 3 ) immSrc [2:0] $end
$var wire 1 * adrSrc $end
$var wire 1 + IRWrite $end
$var wire 2 , ALUSrcB [1:0] $end
$var wire 1 - ALUSrcA $end
$var wire 3 . ALUCtrl [2:0] $end
$scope module CP $end
$var wire 1 ! clk $end
$var wire 1 " reset $end
$var wire 7 / opcode [6:0] $end
$var wire 1 0 invertOp_t $end
$var wire 32 1 instr [31:0] $end
$var wire 7 2 funct7 [6:0] $end
$var wire 3 3 funct3 [2:0] $end
$var parameter 3 4 decode $end
$var parameter 3 5 execute_I $end
$var parameter 3 6 execute_R $end
$var parameter 3 7 fetch $end
$var parameter 3 8 memFetch $end
$var parameter 3 9 memRead $end
$var parameter 3 : writeBack_ALU $end
$var parameter 3 ; writeBack_mem $end
$var reg 3 < ALUCtrl [2:0] $end
$var reg 1 - ALUSrcA $end
$var reg 2 = ALUSrcB [1:0] $end
$var reg 1 + IRWrite $end
$var reg 1 * adrSrc $end
$var reg 3 > currentState [2:0] $end
$var reg 3 ? immSrc [2:0] $end
$var reg 1 ' invertOp $end
$var reg 1 & memWrite $end
$var reg 3 @ nextState [2:0] $end
$var reg 1 % pcUpdate $end
$var reg 1 $ regWrite $end
$var reg 2 A resSrc [1:0] $end
$upscope $end
$scope module DP $end
$var wire 3 B ALUCtrl [2:0] $end
$var wire 1 - ALUSrcA $end
$var wire 2 C ALUSrcB [1:0] $end
$var wire 1 + IRWrite $end
$var wire 1 * adrSrc $end
$var wire 1 ! clk $end
$var wire 3 D immSrc [2:0] $end
$var wire 32 E instOut [31:0] $end
$var wire 1 ' invertOp $end
$var wire 1 & memWrite $end
$var wire 1 % pcUpdate $end
$var wire 1 $ regWrite $end
$var wire 2 F resSrc [1:0] $end
$var wire 1 " reset $end
$var wire 1 G zero $end
$var wire 32 H result [31:0] $end
$var wire 32 I reg2 [31:0] $end
$var wire 32 J reg1 [31:0] $end
$var wire 1 K overflow $end
$var wire 32 L memRead [31:0] $end
$var wire 32 M memIn [31:0] $end
$var wire 32 N instr [31:0] $end
$var wire 32 O currPC [31:0] $end
$var wire 32 P ALURes [31:0] $end
$var wire 32 Q ALUB [31:0] $end
$var wire 32 R ALUA [31:0] $end
$scope module A $end
$var wire 1 ! clk $end
$var wire 1 " reset $end
$var wire 32 S in [31:0] $end
$var reg 32 T out [31:0] $end
$upscope $end
$scope module ALUSrcAMux $end
$var wire 32 U out [31:0] $end
$var wire 1 - sel $end
$var parameter 32 V N $end
$upscope $end
$scope module ALUSrcBMux $end
$var wire 32 W out [31:0] $end
$var wire 2 X sel [1:0] $end
$var parameter 32 Y N $end
$upscope $end
$scope module B $end
$var wire 1 ! clk $end
$var wire 1 " reset $end
$var wire 32 Z in [31:0] $end
$var reg 32 [ out [31:0] $end
$upscope $end
$scope module IRReg $end
$var wire 1 ! clk $end
$var wire 1 + enable $end
$var wire 1 " reset $end
$var wire 32 \ in [31:0] $end
$var reg 32 ] out [31:0] $end
$upscope $end
$scope module PC $end
$var wire 1 ! clk $end
$var wire 1 % pcUpdate $end
$var wire 1 " reset $end
$var wire 32 ^ nextPC [31:0] $end
$var reg 32 _ currPC [31:0] $end
$upscope $end
$scope module adrMux $end
$var wire 32 ` out [31:0] $end
$var wire 1 * sel $end
$var parameter 32 a N $end
$upscope $end
$scope module alu $end
$var wire 32 b A [31:0] $end
$var wire 3 c ALUCtrl [2:0] $end
$var wire 32 d B [31:0] $end
$var wire 1 ' invertOp $end
$var wire 1 K overflow $end
$var wire 1 G zero $end
$var wire 32 e resSub [31:0] $end
$var wire 32 f BEff [31:0] $end
$var reg 32 g ALURes [31:0] $end
$upscope $end
$scope module aluOut $end
$var wire 1 ! clk $end
$var wire 32 h in [31:0] $end
$var wire 1 " reset $end
$var reg 32 i out [31:0] $end
$upscope $end
$scope module immGen $end
$var wire 3 j immSrc [2:0] $end
$var wire 25 k instr [31:7] $end
$var reg 32 l extendedImm [31:0] $end
$upscope $end
$scope module mem $end
$var wire 32 m A1 [31:0] $end
$var wire 32 n WD [31:0] $end
$var wire 1 ! clk $end
$var wire 1 & memWrite $end
$var reg 32 o RD [31:0] $end
$upscope $end
$scope module regFile $end
$var wire 5 p A1 [4:0] $end
$var wire 5 q A2 [4:0] $end
$var wire 5 r A3 [4:0] $end
$var wire 1 ! clk $end
$var wire 1 $ regWrite $end
$var wire 1 " reset $end
$var wire 32 s WD [31:0] $end
$var wire 32 t R2 [31:0] $end
$var wire 32 u R1 [31:0] $end
$upscope $end
$scope module resMux $end
$var wire 32 v out [31:0] $end
$var wire 2 w sel [1:0] $end
$var parameter 32 x N $end
$upscope $end
$upscope $end
$upscope $end
$upscope $end
$enddefinitions $end
$comment Show the parameter values. $end
$dumpall
b100 x
b10 a
b100 Y
b10 V
b111 ;
b100 :
b110 9
b0 8
b1 7
b11 6
b101 5
b10 4
$end
#0
$dumpvars
b0 w
bx v
bx u
bx t
bx s
bx r
bx q
bx p
bx o
bz n
bx m
bx l
bx k
b0 j
bx i
bx h
bx g
bx f
bx e
bx d
b0 c
bx b
bx `
bx _
bx ^
bx ]
bx \
bx [
bx Z
b0 X
bx W
bx U
bx T
bx S
bx R
bx Q
bx P
bx O
bx N
bx M
bx L
xK
bx J
bx I
bx H
xG
b0 F
bx E
b0 D
b0 C
b0 B
b0 A
bx @
b0 ?
bx >
b0 =
b0 <
bx 3
bx 2
bx 1
x0
bx /
b0 .
0-
b0 ,
0+
0*
b0 )
bx (
0'
0&
0%
0$
b0 #
1"
0!
$end
#5000
0K
b0 l
b0 I
b0 Z
b0 t
b0 J
b0 S
b0 u
00
b0 k
b0 r
b0 q
b0 p
b0 /
b0 3
b0 2
b100 P
b100 g
b100 h
b100 f
1+
b1 ,
b1 =
b1 C
b1 X
1%
b1 @
0G
b11111111111111111111111111111100 e
b0 R
b0 U
b0 b
b0 M
b0 `
b0 m
b0 O
b0 _
b0 (
b0 1
b0 E
b0 N
b0 ]
b0 T
b100 Q
b100 W
b100 d
b0 [
b0 H
b0 ^
b0 s
b0 v
b0 i
b0 >
1!
#10000
0!
#15000
b10000000000000000000010010011 L
b10000000000000000000010010011 \
b10000000000000000000010010011 o
1!
#20000
0!
0"
#25000
b100000000 l
b0 P
b0 g
b0 h
b0 f
b1000000000000000000001 k
b1 r
b10011 /
b1000 2
1G
b0 e
b0 Q
b0 W
b0 d
b0 ,
b0 =
b0 C
b0 X
0+
0%
b10 @
b10000000000000000000010010011 (
b10000000000000000000010010011 1
b10000000000000000000010010011 E
b10000000000000000000010010011 N
b10000000000000000000010010011 ]
b100 H
b100 ^
b100 s
b100 v
b100 i
b1 >
1!
#30000
0!
#35000
b100000000 M
b100000000 `
b100000000 m
b100000000 P
b100000000 g
b100000000 h
b100000000 f
1*
b1 #
b1 A
b1 F
b1 w
0G
b11111111111111111111111100000000 e
b100000000 Q
b100000000 W
b100000000 d
b10 ,
b10 =
b10 C
b10 X
1-
b101 @
b10 >
b100000000 H
b100000000 ^
b100000000 s
b100000000 v
b0 i
1!
#40000
0!
#45000
b0 #
b0 A
b0 F
b0 w
0G
b11111111111111111111111100000000 e
b100000000 Q
b100000000 W
b100000000 d
b10 ,
b10 =
b10 C
b10 X
1-
b0 M
b0 `
b0 m
0*
b100 @
b11011110101011011011111011101111 L
b11011110101011011011111011101111 \
b11011110101011011011111011101111 o
b100000000 i
b101 >
1!
#50000
0!
#55000
b100 P
b100 g
b100 h
b100 f
1$
0G
b11111111111111111111111111111100 e
b100 Q
b100 W
b100 d
b1 ,
b1 =
b1 C
b1 X
0-
b0 @
b100 >
b10000000000000000000010010011 L
b10000000000000000000010010011 \
b10000000000000000000010010011 o
1!
#60000
0!
#65000
1+
1%
0G
b11111111111111111111111111111100 e
b100 Q
b100 W
b100 d
b1 ,
b1 =
b1 C
b1 X
0$
b1 @
b100 H
b100 ^
b100 s
b100 v
b100 i
b0 >
1!
#70000
0!
#75000
b0 f
b0 Q
b0 W
b0 d
b0 ,
b0 =
b0 C
b0 X
0+
0%
b10 @
b100 P
b100 g
b100 h
b1 >
0G
b100 e
b100 R
b100 U
b100 b
b100 M
b100 `
b100 m
b100 O
b100 _
1!
#80000
0!
#85000
b100000000 f
b100000000 M
b100000000 `
b100000000 m
b100000000 H
b100000000 ^
b100000000 s
b100000000 v
b100000000 P
b100000000 g
b100000000 h
1*
b1 #
b1 A
b1 F
b1 w
b100000000 Q
b100000000 W
b100000000 d
b10 ,
b10 =
b10 C
b10 X
0G
b11111111111111111111111100000000 e
b0 R
b0 U
b0 b
1-
b101 @
b100000000000000000000100010011 L
b100000000000000000000100010011 \
b100000000000000000000100010011 o
b10 >
1!
#90000
0!
#95000
0G
b0 #
b0 A
b0 F
b0 w
b100000000 Q
b100000000 W
b100000000 d
b10 ,
b10 =
b10 C
b10 X
b11111111111111111111111100000000 e
b0 R
b0 U
b0 b
1-
b100 M
b100 `
b100 m
0*
b100 @
b101 >
b100000000 i
b11011110101011011011111011101111 L
b11011110101011011011111011101111 \
b11011110101011011011111011101111 o
1!
#100000
0!
#105000
b100 f
b1000 P
b1000 g
b1000 h
1G
1$
b100 Q
b100 W
b100 d
b1 ,
b1 =
b1 C
b1 X
b0 e
b100 R
b100 U
b100 b
0-
b0 @
b100000000000000000000100010011 L
b100000000000000000000100010011 \
b100000000000000000000100010011 o
b100 >
1!
#110000
0!
#115000
1+
1%
1G
b0 e
b100 Q
b100 W
b100 d
b1 ,
b1 =
b1 C
b1 X
0$
b1 @
b0 >
b1000 H
b1000 ^
b1000 s
b1000 v
b1000 i
1!
#120000
0!
#125000
b1000000000 l
b0 f
b1000 P
b1000 g
b1000 h
b10000000000000000000010 k
b10 r
b10000 2
b0 Q
b0 W
b0 d
b0 ,
b0 =
b0 C
b0 X
0+
0%
b10 @
0G
b1000 e
b1000 R
b1000 U
b1000 b
b1000 M
b1000 `
b1000 m
b1000 O
b1000 _
b100000000000000000000100010011 (
b100000000000000000000100010011 1
b100000000000000000000100010011 E
b100000000000000000000100010011 N
b100000000000000000000100010011 ]
b1 >
1!
#130000
0!
#135000
b1000000000 f
b1000000000 M
b1000000000 `
b1000000000 m
b1000000000 H
b1000000000 ^
b1000000000 s
b1000000000 v
b1000000000 P
b1000000000 g
b1000000000 h
1*
b1 #
b1 A
b1 F
b1 w
b1000000000 Q
b1000000000 W
b1000000000 d
b10 ,
b10 =
b10 C
b10 X
0G
b11111111111111111111111000000000 e
b0 R
b0 U
b0 b
1-
b101 @
b10 >
b10000000000000110010011 L
b10000000000000110010011 \
b10000000000000110010011 o
1!
#140000
0!
#145000
0G
b0 #
b0 A
b0 F
b0 w
b1000000000 Q
b1000000000 W
b1000000000 d
b10 ,
b10 =
b10 C
b10 X
b11111111111111111111111000000000 e
b0 R
b0 U
b0 b
1-
b1000 M
b1000 `
b1000 m
0*
b100 @
b10001001000100011001101000100 L
b10001001000100011001101000100 \
b10001001000100011001101000100 o
b1000000000 i
b101 >
1!
#150000
0!
#155000
b100 f
b1100 P
b1100 g
b1100 h
1$
b100 Q
b100 W
b100 d
b1 ,
b1 =
b1 C
b1 X
b100 e
b1000 R
b1000 U
b1000 b
0-
b0 @
b100 >
b10000000000000110010011 L
b10000000000000110010011 \
b10000000000000110010011 o
1!
#160000
0!
#165000
1+
1%
b100 e
b100 Q
b100 W
b100 d
b1 ,
b1 =
b1 C
b1 X
0$
b1 @
b1100 H
b1100 ^
b1100 s
b1100 v
b1100 i
b0 >
1!
#170000
0!
#175000
b0 f
b100 l
bx I
bx Z
bx t
b0 Q
b0 W
b0 d
b0 ,
b0 =
b0 C
b0 X
0+
0%
b10 @
b1000000000000011 k
b11 r
b100 q
b0 2
b1100 P
b1100 g
b1100 h
b1 >
b10000000000000110010011 (
b10000000000000110010011 1
b10000000000000110010011 E
b10000000000000110010011 N
b10000000000000110010011 ]
b1100 e
b1100 R
b1100 U
b1100 b
b1100 M
b1100 `
b1100 m
b1100 O
b1100 _
1!
#180000
0!
#185000
b100 M
b100 `
b100 m
b100 H
b100 ^
b100 s
b100 v
b100 P
b100 g
b100 h
b100 f
1*
b1 #
b1 A
b1 F
b1 w
b10 ,
b10 =
b10 C
b10 X
b0 R
b0 U
b0 b
1-
b101 @
b1010010100000011 L
b1010010100000011 \
b1010010100000011 o
0G
b11111111111111111111111111111100 e
b100 Q
b100 W
b100 d
bx [
b10 >
1!
#190000
0!
#195000
b0 #
b0 A
b0 F
b0 w
0G
b100 Q
b100 W
b100 d
b10 ,
b10 =
b10 C
b10 X
b11111111111111111111111111111100 e
b0 R
b0 U
b0 b
1-
b1100 M
b1100 `
b1100 m
0*
b100 @
b101 >
b100 i
b100000000000000000000100010011 L
b100000000000000000000100010011 \
b100000000000000000000100010011 o
1!
#200000
0!
#205000
b10000 P
b10000 g
b10000 h
1$
0G
b100 Q
b100 W
b100 d
b1 ,
b1 =
b1 C
b1 X
b1000 e
b1100 R
b1100 U
b1100 b
0-
b0 @
b1010010100000011 L
b1010010100000011 \
b1010010100000011 o
b100 >
1!
#210000
0!
#215000
1+
1%
0G
b1000 e
b100 Q
b100 W
b100 d
b1 ,
b1 =
b1 C
b1 X
0$
b1 @
b0 >
b10000 H
b10000 ^
b10000 s
b10000 v
b10000 i
1!
#220000
0!
#225000
xK
b0 l
b0 I
b0 Z
b0 t
b100000000 J
b100000000 S
b100000000 u
bx f
bx P
bx g
bx h
b101001010 k
b1010 r
b0 q
b1 p
b11 /
b10 3
xG
bx Q
bx W
bx d
b0 ,
b0 =
b0 C
b0 X
0+
0%
b10 @
bx e
b10000 R
b10000 U
b10000 b
b10000 M
b10000 `
b10000 m
b10000 O
b10000 _
b1010010100000011 (
b1010010100000011 1
b1010010100000011 E
b1010010100000011 N
b1010010100000011 ]
b1 >
1!
#230000
0!
#235000
0K
b100000000 M
b100000000 `
b100000000 m
1*
b1 #
b1 A
b1 F
b1 w
b10 ,
b10 =
b10 C
b10 X
b100000000 R
b100000000 U
b100000000 b
1-
b110 @
b100000000 P
b100000000 g
b100000000 h
b0 f
b10 >
b100000000 H
b100000000 ^
b100000000 s
b100000000 v
bx i
0G
b100000000 e
b0 Q
b0 W
b0 d
b0 [
b100000000 T
b10000001010010110000011 L
b10000001010010110000011 \
b10000001010010110000011 o
1!
#240000
0!
#245000
b10000 P
b10000 g
b10000 h
b0 #
b0 A
b0 F
b0 w
b0 ,
b0 =
b0 C
b0 X
b10000 e
b10000 R
b10000 U
b10000 b
0-
b100000000 M
b100000000 `
b100000000 m
1*
b111 @
b11011110101011011011111011101111 L
b11011110101011011011111011101111 \
b11011110101011011011111011101111 o
b100000000 i
b110 >
1!
#250000
0!
#255000
b10100 P
b10100 g
b10100 h
b100 f
b1100 e
b100 Q
b100 W
b100 d
b1 ,
b1 =
b1 C
b1 X
1$
b10 #
b10 A
b10 F
b10 w
0*
b0 @
b111 >
b10000 M
b10000 `
b10000 m
b11011110101011011011111011101111 H
b11011110101011011011111011101111 ^
b11011110101011011011111011101111 s
b11011110101011011011111011101111 v
b10000 i
1!
#260000
0!
#265000
1+
1%
b0 #
b0 A
b0 F
b0 w
b1100 e
b100 Q
b100 W
b100 d
b1 ,
b1 =
b1 C
b1 X
0$
b1 @
b10100 H
b10100 ^
b10100 s
b10100 v
b10000001010010110000011 L
b10000001010010110000011 \
b10000001010010110000011 o
b10100 i
b0 >
1!
#270000
0!
#275000
b0 f
b100 l
bx I
bx Z
bx t
b0 Q
b0 W
b0 d
b0 ,
b0 =
b0 C
b0 X
0+
0%
b10 @
b1000000101001011 k
b1011 r
b100 q
b10100 P
b10100 g
b10100 h
b1 >
b10000001010010110000011 (
b10000001010010110000011 1
b10000001010010110000011 E
b10000001010010110000011 N
b10000001010010110000011 ]
b10100 e
b10100 R
b10100 U
b10100 b
b10100 M
b10100 `
b10100 m
b10100 O
b10100 _
1!
#280000
0!
#285000
b100000100 M
b100000100 `
b100000100 m
b100000100 H
b100000100 ^
b100000100 s
b100000100 v
b100000100 P
b100000100 g
b100000100 h
b100 f
1*
b1 #
b1 A
b1 F
b1 w
b10 ,
b10 =
b10 C
b10 X
b100000000 R
b100000000 U
b100000000 b
1-
b110 @
b100000001010011000000011 L
b100000001010011000000011 \
b100000001010011000000011 o
0G
b11111100 e
b100 Q
b100 W
b100 d
bx [
b10 >
1!
#290000
0!
#295000
xK
bx f
bx P
bx g
bx h
b0 #
b0 A
b0 F
b0 w
xG
bx Q
bx W
bx d
b0 ,
b0 =
b0 C
b0 X
bx e
b10100 R
b10100 U
b10100 b
0-
b100000100 M
b100000100 `
b100000100 m
1*
b111 @
b110 >
b100000100 i
b11001010111111101011101010111110 L
b11001010111111101011101010111110 \
b11001010111111101011101010111110 o
1!
#300000
0!
#305000
0K
b11000 P
b11000 g
b11000 h
b100 f
0G
b10000 e
b100 Q
b100 W
b100 d
b1 ,
b1 =
b1 C
b1 X
1$
b10 #
b10 A
b10 F
b10 w
0*
b0 @
b10100 M
b10100 `
b10100 m
b11001010111111101011101010111110 H
b11001010111111101011101010111110 ^
b11001010111111101011101010111110 s
b11001010111111101011101010111110 v
bx i
b111 >
1!
#310000
0!
#315000
1+
1%
b0 #
b0 A
b0 F
b0 w
0G
b10000 e
b100 Q
b100 W
b100 d
b1 ,
b1 =
b1 C
b1 X
0$
b1 @
b0 >
b11000 i
b11000 H
b11000 ^
b11000 s
b11000 v
b100000001010011000000011 L
b100000001010011000000011 \
b100000001010011000000011 o
1!
#320000
0!
