multi-cycle/src/core/ControlUnit.v
module controlUnit(
    input clk,
    input reset,
    input [31:0] instr,
    output logic pcUpdate,
    output logic adrSrc,
    output logic memWrite,
    output logic [2:0] formatCtrl,
    output logic IRWrite,
    output logic regWrite,
    output logic [2:0] immSrc,
    output logic ALUSrcA,
    output logic [1:0] ALUSrcB,
    output logic invertOp,
    output logic [2:0] ALUCtrl,
    output logic [1:0] resSrc
);
    
    wire [6:0] funct7;
    wire [2:0] funct3; 
    wire [6:0] opcode;
    wire invertOp_t;

    assign funct7 = instr[31:25];
    assign funct3 = instr[14:12];
    assign opcode = instr[6:0];
    assign invertOp_t = funct7[5];

    
    localparam memFetch = 4'd0;
    localparam fetch = 4'd1;
    localparam decode = 4'd2;
    localparam execute_R = 4'd3;
    localparam writeBack_ALU = 4'd4;
    localparam execute_I = 4'd5;
    localparam memRead = 4'd6;
    localparam writeBack_mem = 4'd7;
    localparam memStore = 4'd8;
    localparam pcSet = 4'd9;

    logic [3:0] currentState, nextState;

    //MAIN FSM
    //NEXT STATE LOGIC
    always_comb begin
        nextState = currentState; //Default Case
        case(currentState)
            memFetch: nextState = fetch;
            fetch: nextState = decode;
            decode: begin
                case(opcode)
                    7'b0110011: nextState = execute_R;
                    7'b0010011: nextState = execute_I;
                    7'b0000011: nextState = memRead;
                    7'b0100011: nextState = memStore;
                endcase
            end
            execute_R: nextState = writeBack_ALU;
            execute_I: nextState = writeBack_ALU;
            memRead: nextState = writeBack_mem;
            memStore: nextState = pcSet;
            pcSet: nextState = memFetch;
            writeBack_mem: nextState = memFetch;
            writeBack_ALU: nextState = memFetch;
        endcase
    end

    //FSM REGISTER
    always_ff @(posedge clk) begin
        if(reset)
            currentState <= memFetch;
        else
            currentState <= nextState;
    end

    //OUTPUT LOGIC
    always_comb begin
        pcUpdate = 0;
        adrSrc = 0;
        memWrite = 0;
        formatCtrl = 3'b010;
        IRWrite = 0;
        regWrite = 0;
        immSrc = 3'd0;
        ALUSrcA = 0;
        ALUSrcB = 2'd0;
        invertOp = 0;
        resSrc = 2'd0;
        case(currentState)
            memFetch: begin
                adrSrc = 0;
                pcUpdate = 1;
                ALUSrcA = 0;        //Setting ALU to calculate PC+4 here to support correct PC update after reset
                ALUSrcB = 2'd1;
                resSrc = 2'd0;
                IRWrite = 1;
            end
            fetch: begin
                //IRWrite = 1;
            end
            decode: begin
                ALUSrcA = 1;
                ALUSrcB = 2'd2;
                resSrc = 2'd1;
                adrSrc = 1;
                if(opcode == 7'b0000011)
                    immSrc = 3'b000;
                else
                    immSrc = 3'b001;
            end
            memRead: begin
                resSrc = 2'd0;
                adrSrc = 1;
                formatCtrl = funct3;
            end
            memStore: begin
                resSrc = 2'd0;
                adrSrc = 1;
                memWrite = 1;
                formatCtrl = funct3;
            end
            pcSet: begin
                ALUSrcA = 0;
                ALUSrcB = 2'd1;
            end
            writeBack_mem: begin
                resSrc = 2'd2;
                regWrite = 1;
                ALUSrcA = 0;
                ALUSrcB = 2'd1;
                formatCtrl = funct3;
            end
            execute_R: begin
                ALUSrcA = 1;
                ALUSrcB = 2'd0;
                invertOp = invertOp_t;
            end
            execute_I: begin
                ALUSrcA = 1;
                ALUSrcB = 2'd2;
                immSrc = 3'd0;
                if(funct3 == 3'b101)
                    invertOp = invertOp_t;
            end
            writeBack_ALU: begin
                resSrc = 2'd0;
                regWrite = 1;
                ALUSrcA = 0;
                ALUSrcB = 2'd1;
            end
        endcase
    end

    //ALU DECODER
    always_comb begin
        ALUCtrl = 3'd0;
        case(currentState)
            memFetch: ALUCtrl = 3'b000;
            decode: ALUCtrl = 3'b000;
            memStore: ALUCtrl = 3'b000;
            pcSet: ALUCtrl = 3'b000;
            execute_R: ALUCtrl = funct3;
            execute_I: ALUCtrl = funct3;
            writeBack_mem: ALUCtrl = 3'b000;
            writeBack_ALU: ALUCtrl = 3'b000;
        endcase
    end
endmodule

multi-cycle/src/blocks/ImmediateGenerator.v
module immediateGenerator(input [31:7] instr, input [2:0] immSrc, output reg [31:0] extendedImm);

    always @(*) begin
        extendedImm = 0;
        case(immSrc)
            3'b000: extendedImm = {{20{instr[31]}}, instr[31:20]}; //I Type
            3'b001: extendedImm = {{20{instr[31]}}, instr[31:25], instr[11:7]}; //S Type
            3'b010: extendedImm = {{20{instr[31]}}, instr[7], instr[30:25], instr[11:8], 1'b0}; //B Type
            3'b011: extendedImm = {instr[31:12], 12'b0}; //U type
            3'b100: extendedImm = {{11{instr[31]}}, instr[31], instr[20], instr[19:12], instr[30:21], 1'b0}; //J Type
            default: extendedImm = 32'b0;
        endcase
        //$display("%0d", extendedImm);
    end

endmodule

multi-cycle/src/blocks/ALU.v
module ALU(
    input [31:0] A,
    input [31:0] B,
    input invertOp,
    input [2:0] ALUCtrl,
    output reg [31:0] ALURes,
    output zero,
    output overflow
);
    wire [31:0] BEff;
    wire [31:0] resSub;
    assign BEff = (invertOp)? (~B + 1) : B;
    assign resSub = A-B;
    assign overflow = (A[31] != B[31]) && (resSub[31] != A[31]);
    assign zero = (resSub == 0);
    always @(*) begin
      case(ALUCtrl)
        3'b000: ALURes = A+BEff; //ADD/Sub
        3'b001: ALURes = A << B[4:0]; //SLL
        3'b010: ALURes = {31'b0, $signed(A) < $signed(B)}; //SLT
        3'b011: ALURes = A < B; //SLTU
        3'b100: ALURes = A ^ B; //XOR
        3'b101: ALURes = (!invertOp)? (A >> B[4:0]) : ($signed(A) >> B[4:0]); //SRL/SRA
        3'b110: ALURes = A | B;
        3'b111: ALURes = A & B;
      endcase
    end

endmodule

multi-cycle/src/utils/nMux.v
module nMux #(
    parameter N = 4
)(
    input [31:0] in [N-1:0],
    input [$clog2(N)-1:0] sel,
    output [31:0] out
);
    assign out = in[sel];
endmodule

multi-cycle/src/utils/Reg32.v
module reg32(
    input clk,
    input reset,
    input [31:0] in,
    output reg [31:0] out
);

    always @(posedge clk) begin
        if(reset)
            out <= 32'b0;
        else
            out <= in;
    end
endmodule

module enReg32(
    input clk,
    input reset,
    input enable,
    input [31:0] in,
    output reg [31:0] out
);
    always @(posedge clk) begin
        if(reset)
            out <= 32'b0;
        else if(enable)
            out <= in;
    end
endmodule

multi-cycle/src/blocks/Memory.v
module memory(
    input clk,
    input memWrite,
    input [2:0] formatCtrl,
    input [31:0] A1,
    input [31:0] WD,
    output reg [31:0] RD
);

    
    reg [31:0] mem [0:2047];
    reg [31:0] rawRead;
    reg [1:0] bytePos;
    wire [3:0] byteMask;
    wire [31:0] fWrite;

    //Synchronous Memory
    always @(posedge clk) begin
        rawRead <= mem[A1[12:2]];
        bytePos <= A1[1:0];
        if(memWrite) begin
            if(byteMask[0])
                mem[A1[12:2]][7:0] <= fWrite[7:0];
            if(byteMask[1])
                mem[A1[12:2]][15:8] <= fWrite[15:8];
            if(byteMask[2])
                mem[A1[12:2]][23:16] <= fWrite[23:16];
            if(byteMask[3])
                mem[A1[12:2]][31:24] <= fWrite[31:24];
            
            //$display("MEM WRITE: addr=%h data=%h" , A1, fWrite);
        end
    end

    loadFormatter lf(.dataIn(rawRead), .formatCtrl(formatCtrl), .bytePos(bytePos), .dataOut(RD));
    storeFormatter sf(.dataIn(WD), .formatCtrl(formatCtrl), .bytePos(bytePos), .byteMask(byteMask), .dataOut(fWrite));

    initial begin
        $readmemh("sim/program.hex", mem);
    end

endmodule

module loadFormatter(
    input [31:0] dataIn,
    input [2:0] formatCtrl,
    input [1:0] bytePos,
    output reg [31:0] dataOut
);
    wire [7:0] byte_data;
    wire [15:0] half_data;
    assign byte_data = dataIn[bytePos*8 +: 8];
    assign half_data = dataIn[bytePos[1]*16 +: 16];
    wire byte_data_sign, half_data_sign;
    assign byte_data_sign = byte_data[7];
    assign half_data_sign = half_data[15];

    always_comb begin
        case(formatCtrl)
            3'b000: dataOut = {{24{byte_data_sign}}, byte_data}; //LB
            3'b001: dataOut = {{16{half_data_sign}}, half_data}; //LH
            3'b010: dataOut = dataIn; //LW
            3'b100: dataOut = {24'b0, byte_data}; //LBU
            3'b101: dataOut = {16'b0, half_data}; //LHU
            default: dataOut = dataIn;
        endcase
        //$display(bytePos, byte_start);
    end
endmodule

module storeFormatter(
    input [31:0] dataIn,
    input [2:0] formatCtrl,
    input [1:0] bytePos,
    output reg [3:0] byteMask,
    output reg [31:0] dataOut
);
    always @(*) begin
        case(formatCtrl)
            3'b000: begin //SB
                dataOut = dataIn << 8*bytePos;
                byteMask = 4'b0001 << bytePos;
            end
            3'b001: begin //SH
                dataOut = dataIn << 16*bytePos[1];
                byteMask = 4'b0011 << 2*bytePos[1];
            end
            3'b010: begin //SW
                dataOut = dataIn;
                byteMask = 4'b1111;
            end
        endcase
    end
endmodule

multi-cycle/src/blocks/RegisterFile.v
module registerFile(
    input clk,
    input reset,
    input regWrite,
    input [4:0] A1,
    input [4:0] A2,
    input [4:0] A3,
    input [31:0] WD,
    output [31:0] R1,
    output [31:0] R2
);

    reg [31:0] rFile [31:0];
    assign R1 = (A1 == 0)? 32'b0:rFile[A1];
    assign R2 = (A2 == 0)? 32'b0:rFile[A2];

    always @(posedge clk) begin
        if(reset) begin
            rFile[0] = 32'd0;
        end
        else if(regWrite && (A3 != 0)) begin
            rFile[A3] <= WD;
            $display("Write: x%0d = %0d (0x%h) time=%0t", A3, WD, WD, $time);
        end
    end

endmodule

multi-cycle/src/blocks/ProgramCounter.v
module programCounter(
    input clk,
    input reset,
    input pcUpdate,
    input [31:0] nextPC,
    output reg [31:0] currPC
);
    always @(posedge clk) begin
        if(reset)
            currPC <= 32'b0;
        else if(pcUpdate)
            currPC <= nextPC;
    end
endmodule

multi-cycle/src/core/datapath.v
module dataPath(
    input clk,
    input reset,
    input pcUpdate,
    input adrSrc,
    input memWrite,
    input [2:0] formatCtrl,
    input IRWrite,
    input regWrite,
    input [2:0] immSrc,
    input ALUSrcA,
    input [1:0] ALUSrcB,
    input invertOp,
    input [2:0] ALUCtrl,
    input [1:0] resSrc,
    output [31:0] instOut
);
    wire [31:0] currPC;
    wire [31:0] adrMuxIn [1:0];
    wire [31:0] memIn;
    wire [31:0] memRead;
    wire [31:0] instr;
    wire [31:0] reg1, reg2; // Register File Outputs
    wire [31:0] ALUSrcAMuxIn [1:0];
    wire [31:0] ALUSrcBMuxIn [3:0];
    wire [31:0] ALUA, ALUB;
    wire [31:0] ALURes;
    wire [31:0] resMuxIn [3:0];
    wire [31:0] result;
    wire zero, overflow;


    //Architectural State Elements
    programCounter PC(.clk(clk), .reset(reset), .pcUpdate(pcUpdate), .nextPC(result), .currPC(currPC));
    registerFile regFile(.clk(clk), .reset(reset), .regWrite(regWrite), .A1(instr[19:15]), .A2(instr[24:20]), .A3(instr[11:7]), .WD(result), .R1(reg1), .R2(reg2));
    memory mem(.clk(clk), .memWrite(memWrite), .formatCtrl(formatCtrl), .A1(memIn), .WD(ALUSrcBMuxIn[0]), .RD(memRead));
    
    //Non Architectural State Elements
    enReg32 IRReg(.clk(clk), .reset(reset), .enable(IRWrite), .in(memRead), .out(instr));
    reg32 A(.clk(clk), .reset(reset), .in(reg1), .out(ALUSrcAMuxIn[1]));
    reg32 B(.clk(clk), .reset(reset), .in(reg2), .out(ALUSrcBMuxIn[0]));
    reg32 aluOut(.clk(clk), .reset(reset), .in(ALURes), .out(resMuxIn[0]));

    //Combinational Elements
    assign adrMuxIn[0] = currPC;
    assign adrMuxIn[1] = result;
    nMux #(.N(2)) adrMux(.in(adrMuxIn), .sel(adrSrc), .out(memIn));

    assign ALUSrcAMuxIn[0] = currPC;
    assign ALUSrcBMuxIn[1] = 32'd4;
    assign ALUSrcBMuxIn[3] = 32'd0;
    nMux #(.N(2)) ALUSrcAMux(.in(ALUSrcAMuxIn), .sel(ALUSrcA), .out(ALUA));
    nMux #(.N(4)) ALUSrcBMux(.in(ALUSrcBMuxIn), .sel(ALUSrcB), .out(ALUB));
    
    assign resMuxIn[1] = ALURes;
    assign resMuxIn[2] = memRead;
    assign resMuxIn[3] = 32'd0;
    nMux #(.N(4)) resMux(.in(resMuxIn), .sel(resSrc), .out(result));

    ALU alu(.A(ALUA), .B(ALUB), .invertOp(invertOp), .ALUCtrl(ALUCtrl), .ALURes(ALURes), .zero(zero), .overflow(overflow));
    immediateGenerator immGen(.instr(instr[31:7]), .immSrc(immSrc), .extendedImm(ALUSrcBMuxIn[2]));

    assign instOut = instr;
endmodule

multi-cycle/src/core/cpu.v
module CPU(
    input clk,
    input reset
);
    //Control Wires
    wire pcUpdate;
    wire adrSrc;
    wire memWrite;
    wire [2:0] formatCtrl;
    wire IRWrite;
    wire regWrite;
    wire [2:0] immSrc;
    wire ALUSrcA;
    wire [1:0] ALUSrcB;
    wire invertOp;
    wire [2:0] ALUCtrl;
    wire [1:0] resSrc;
    wire [31:0] instr;

    dataPath DP(
        .clk(clk),
        .reset(reset),
        .pcUpdate(pcUpdate),
        .adrSrc(adrSrc),
        .memWrite(memWrite),
        .formatCtrl(formatCtrl),
        .IRWrite(IRWrite),
        .regWrite(regWrite),
        .immSrc(immSrc),
        .ALUSrcA(ALUSrcA),
        .ALUSrcB(ALUSrcB),
        .invertOp(invertOp),
        .ALUCtrl(ALUCtrl),
        .resSrc(resSrc),
        .instOut(instr)
    );

    controlUnit CP(
        .clk(clk),
        .reset(reset),
        .instr(instr),
        .pcUpdate(pcUpdate),
        .adrSrc(adrSrc),
        .memWrite(memWrite),
        .formatCtrl(formatCtrl),
        .IRWrite(IRWrite),
        .regWrite(regWrite),
        .immSrc(immSrc),
        .ALUSrcA(ALUSrcA),
        .ALUSrcB(ALUSrcB),
        .invertOp(invertOp),
        .ALUCtrl(ALUCtrl),
        .resSrc(resSrc)
    );
endmodule

multi-cycle/sim/cpu_tb.v
`timescale 1ns/1ns

module cpu_tb();
    reg clk;
    reg reset;

    initial begin
        clk = 0;
        forever #5 clk = ~clk;
    end

    CPU DUT(.clk(clk), .reset(reset));
    initial begin
        $dumpfile("wave.vcd");
        $dumpvars(0, cpu_tb);
        reset = 1; #20
        reset = 0; #5000
        $finish;
    end
endmodule

multi-cycle/wave.vcd
$date
	Tue Jun  9 00:07:35 2026
$end
$version
	Icarus Verilog
$end
$timescale
	1ns
$end
$scope module cpu_tb $end
$var reg 1 ! clk $end
$var reg 1 " reset $end
$scope module DUT $end
$var wire 1 ! clk $end
$var wire 1 " reset $end
$var wire 2 # resSrc [1:0] $end
$var wire 1 $ regWrite $end
$var wire 1 % pcUpdate $end
$var wire 1 & memWrite $end
$var wire 1 ' invertOp $end
$var wire 32 ( instr [31:0] $end
$var wire 3 ) immSrc [2:0] $end
$var wire 3 * formatCtrl [2:0] $end
$var wire 1 + adrSrc $end
$var wire 1 , IRWrite $end
$var wire 2 - ALUSrcB [1:0] $end
$var wire 1 . ALUSrcA $end
$var wire 3 / ALUCtrl [2:0] $end
$scope module CP $end
$var wire 1 ! clk $end
$var wire 1 " reset $end
$var wire 7 0 opcode [6:0] $end
$var wire 1 1 invertOp_t $end
$var wire 32 2 instr [31:0] $end
$var wire 7 3 funct7 [6:0] $end
$var wire 3 4 funct3 [2:0] $end
$var parameter 4 5 decode $end
$var parameter 4 6 execute_I $end
$var parameter 4 7 execute_R $end
$var parameter 4 8 fetch $end
$var parameter 4 9 memFetch $end
$var parameter 4 : memRead $end
$var parameter 4 ; memStore $end
$var parameter 4 < pcSet $end
$var parameter 4 = writeBack_ALU $end
$var parameter 4 > writeBack_mem $end
$var reg 3 ? ALUCtrl [2:0] $end
$var reg 1 . ALUSrcA $end
$var reg 2 @ ALUSrcB [1:0] $end
$var reg 1 , IRWrite $end
$var reg 1 + adrSrc $end
$var reg 4 A currentState [3:0] $end
$var reg 3 B formatCtrl [2:0] $end
$var reg 3 C immSrc [2:0] $end
$var reg 1 ' invertOp $end
$var reg 1 & memWrite $end
$var reg 4 D nextState [3:0] $end
$var reg 1 % pcUpdate $end
$var reg 1 $ regWrite $end
$var reg 2 E resSrc [1:0] $end
$upscope $end
$scope module DP $end
$var wire 3 F ALUCtrl [2:0] $end
$var wire 1 . ALUSrcA $end
$var wire 2 G ALUSrcB [1:0] $end
$var wire 1 , IRWrite $end
$var wire 1 + adrSrc $end
$var wire 1 ! clk $end
$var wire 3 H formatCtrl [2:0] $end
$var wire 3 I immSrc [2:0] $end
$var wire 32 J instOut [31:0] $end
$var wire 1 ' invertOp $end
$var wire 1 & memWrite $end
$var wire 1 % pcUpdate $end
$var wire 1 $ regWrite $end
$var wire 2 K resSrc [1:0] $end
$var wire 1 " reset $end
$var wire 1 L zero $end
$var wire 32 M result [31:0] $end
$var wire 32 N reg2 [31:0] $end
$var wire 32 O reg1 [31:0] $end
$var wire 1 P overflow $end
$var wire 32 Q memRead [31:0] $end
$var wire 32 R memIn [31:0] $end
$var wire 32 S instr [31:0] $end
$var wire 32 T currPC [31:0] $end
$var wire 32 U ALURes [31:0] $end
$var wire 32 V ALUB [31:0] $end
$var wire 32 W ALUA [31:0] $end
$scope module A $end
$var wire 1 ! clk $end
$var wire 1 " reset $end
$var wire 32 X in [31:0] $end
$var reg 32 Y out [31:0] $end
$upscope $end
$scope module ALUSrcAMux $end
$var wire 32 Z out [31:0] $end
$var wire 1 . sel $end
$var parameter 32 [ N $end
$upscope $end
$scope module ALUSrcBMux $end
$var wire 32 \ out [31:0] $end
$var wire 2 ] sel [1:0] $end
$var parameter 32 ^ N $end
$upscope $end
$scope module B $end
$var wire 1 ! clk $end
$var wire 1 " reset $end
$var wire 32 _ in [31:0] $end
$var reg 32 ` out [31:0] $end
$upscope $end
$scope module IRReg $end
$var wire 1 ! clk $end
$var wire 1 , enable $end
$var wire 1 " reset $end
$var wire 32 a in [31:0] $end
$var reg 32 b out [31:0] $end
$upscope $end
$scope module PC $end
$var wire 1 ! clk $end
$var wire 1 % pcUpdate $end
$var wire 1 " reset $end
$var wire 32 c nextPC [31:0] $end
$var reg 32 d currPC [31:0] $end
$upscope $end
$scope module adrMux $end
$var wire 32 e out [31:0] $end
$var wire 1 + sel $end
$var parameter 32 f N $end
$upscope $end
$scope module alu $end
$var wire 32 g A [31:0] $end
$var wire 3 h ALUCtrl [2:0] $end
$var wire 32 i B [31:0] $end
$var wire 1 ' invertOp $end
$var wire 1 P overflow $end
$var wire 1 L zero $end
$var wire 32 j resSub [31:0] $end
$var wire 32 k BEff [31:0] $end
$var reg 32 l ALURes [31:0] $end
$upscope $end
$scope module aluOut $end
$var wire 1 ! clk $end
$var wire 32 m in [31:0] $end
$var wire 1 " reset $end
$var reg 32 n out [31:0] $end
$upscope $end
$scope module immGen $end
$var wire 3 o immSrc [2:0] $end
$var wire 25 p instr [31:7] $end
$var reg 32 q extendedImm [31:0] $end
$upscope $end
$scope module mem $end
$var wire 32 r A1 [31:0] $end
$var wire 32 s WD [31:0] $end
$var wire 1 ! clk $end
$var wire 3 t formatCtrl [2:0] $end
$var wire 1 & memWrite $end
$var wire 32 u fWrite [31:0] $end
$var wire 4 v byteMask [3:0] $end
$var wire 32 w RD [31:0] $end
$var reg 2 x bytePos [1:0] $end
$var reg 32 y rawRead [31:0] $end
$scope module lf $end
$var wire 2 z bytePos [1:0] $end
$var wire 32 { dataIn [31:0] $end
$var wire 3 | formatCtrl [2:0] $end
$var wire 1 } half_data_sign $end
$var wire 16 ~ half_data [15:0] $end
$var wire 1 !" byte_data_sign $end
$var wire 8 "" byte_data [7:0] $end
$var reg 32 #" dataOut [31:0] $end
$upscope $end
$scope module sf $end
$var wire 2 $" bytePos [1:0] $end
$var wire 32 %" dataIn [31:0] $end
$var wire 3 &" formatCtrl [2:0] $end
$var reg 4 '" byteMask [3:0] $end
$var reg 32 (" dataOut [31:0] $end
$upscope $end
$upscope $end
$scope module regFile $end
$var wire 5 )" A1 [4:0] $end
$var wire 5 *" A2 [4:0] $end
$var wire 5 +" A3 [4:0] $end
$var wire 1 ! clk $end
$var wire 1 $ regWrite $end
$var wire 1 " reset $end
$var wire 32 ," WD [31:0] $end
$var wire 32 -" R2 [31:0] $end
$var wire 32 ." R1 [31:0] $end
$upscope $end
$scope module resMux $end
$var wire 32 /" out [31:0] $end
$var wire 2 0" sel [1:0] $end
$var parameter 32 1" N $end
$upscope $end
$upscope $end
$upscope $end
$upscope $end
$enddefinitions $end
$comment Show the parameter values. $end
$dumpall
b100 1"
b10 f
b100 ^
b10 [
b111 >
b100 =
b1001 <
b1000 ;
b110 :
b0 9
b1 8
b11 7
b101 6
b10 5
$end
#0
$dumpvars
b0 0"
bx /"
bx ."
bx -"
bx ,"
bx +"
bx *"
bx )"
bx ("
b1111 '"
b10 &"
bx %"
bx $"
bx #"
bx ""
x!"
bx ~
x}
b10 |
bx {
bx z
bx y
bx x
bx w
b1111 v
bx u
b10 t
bx s
bx r
bx q
bx p
b0 o
bx n
bx m
bx l
bx k
bx j
bx i
b0 h
bx g
bx e
bx d
bx c
bx b
bx a
bx `
bx _
b0 ]
bx \
bx Z
bx Y
bx X
bx W
bx V
bx U
bx T
bx S
bx R
bx Q
xP
bx O
bx N
bx M
xL
b0 K
bx J
b0 I
b10 H
b0 G
b0 F
b0 E
bx D
b0 C
b10 B
bx A
b0 @
b0 ?
bx 4
bx 3
bx 2
x1
bx 0
b0 /
0.
b0 -
0,
0+
b10 *
b0 )
bx (
0'
0&
0%
0$
b0 #
1"
0!
$end
#5
0P
b0 q
b0 N
b0 _
b0 -"
b0 O
b0 X
b0 ."
01
b0 p
b0 +"
b0 *"
b0 )"
b0 0
b0 4
b0 3
b0 u
b0 ("
b100 U
b100 l
b100 m
b100 k
1,
b1 -
b1 @
b1 G
b1 ]
1%
b1 D
0L
b11111111111111111111111111111100 j
b0 W
b0 Z
b0 g
b0 R
b0 e
b0 r
b0 T
b0 d
b0 (
b0 2
b0 J
b0 S
b0 b
b0 Y
b100 V
b100 \
b100 i
b0 `
b0 s
b0 %"
b0 M
b0 c
b0 ,"
b0 /"
b0 n
b0 A
1!
#10
0!
#15
0}
1!"
b10010011 ~
b110000000000000000000010010011 Q
b110000000000000000000010010011 a
b110000000000000000000010010011 w
b110000000000000000000010010011 #"
b10010011 ""
b0 x
b0 z
b0 $"
b110000000000000000000010010011 y
b110000000000000000000010010011 {
1!
#20
0!
0"
#25
b1100000000 q
b0 U
b0 l
b0 m
b0 k
b11000000000000000000001 p
b1 +"
b10011 0
b11000 3
1L
b0 j
b0 V
b0 \
b0 i
b0 -
b0 @
b0 G
b0 ]
0,
0%
b10 D
b110000000000000000000010010011 (
b110000000000000000000010010011 2
b110000000000000000000010010011 J
b110000000000000000000010010011 S
b110000000000000000000010010011 b
b100 M
b100 c
b100 ,"
b100 /"
b100 n
b1 A
1!
#30
0!
#35
b1100000001 q
b1100000001 R
b1100000001 e
b1100000001 r
b1100000001 U
b1100000001 l
b1100000001 m
b1100000001 k
b1 )
b1 C
b1 I
b1 o
1+
b1 #
b1 E
b1 K
b1 0"
0L
b11111111111111111111110011111111 j
b1100000001 V
b1100000001 \
b1100000001 i
b10 -
b10 @
b10 G
b10 ]
1.
b101 D
b10 A
b1100000001 M
b1100000001 c
b1100000001 ,"
b1100000001 /"
b0 n
1!
#40
0!
#45
b1100000000 U
b1100000000 l
b1100000000 m
b1100000000 k
b1100000000 q
x!"
x}
bx Q
bx a
bx w
bx #"
b0 #
b0 E
b0 K
b0 0"
0L
b11111111111111111111110100000000 j
b1100000000 V
b1100000000 \
b1100000000 i
b10 -
b10 @
b10 G
b10 ]
1.
b0 )
b0 C
b0 I
b0 o
b0 R
b0 e
b0 r
0+
b100 D
b1 x
b1 z
b1 $"
bx ""
bx ~
bx y
bx {
b1100000001 n
b101 A
1!
#50
0!
#55
b100 U
b100 l
b100 m
b100 k
1$
0L
b11111111111111111111111111111100 j
b100 V
b100 \
b100 i
b1 -
b1 @
b1 G
b1 ]
0.
b0 D
1!"
0}
b110000000000000000000010010011 Q
b110000000000000000000010010011 a
b110000000000000000000010010011 w
b110000000000000000000010010011 #"
b100 A
b1100000000 M
b1100000000 c
b1100000000 ,"
b1100000000 /"
b1100000000 n
b0 x
b0 z
b0 $"
b10010011 ""
b10010011 ~
b110000000000000000000010010011 y
b110000000000000000000010010011 {
1!
#60
0!
#65
1,
1%
0L
b11111111111111111111111111111100 j
b100 V
b100 \
b100 i
b1 -
b1 @
b1 G
b1 ]
0$
b1 D
b100 M
b100 c
b100 ,"
b100 /"
b100 n
b0 A
1!
#70
0!
#75
b0 k
b0 V
b0 \
b0 i
b0 -
b0 @
b0 G
b0 ]
0,
0%
b10 D
b100 U
b100 l
b100 m
b1 A
0L
b100 j
b100 W
b100 Z
b100 g
b100 R
b100 e
b100 r
b100 T
b100 d
1!
#80
0!
#85
b1100000001 q
b1100000001 k
b1100000001 R
b1100000001 e
b1100000001 r
b1100000001 M
b1100000001 c
b1100000001 ,"
b1100000001 /"
b1100000001 U
b1100000001 l
b1100000001 m
0!"
b100001000000000000100010011 Q
b100001000000000000100010011 a
b100001000000000000100010011 w
b100001000000000000100010011 #"
b1 )
b1 C
b1 I
b1 o
1+
b1 #
b1 E
b1 K
b1 0"
b1100000001 V
b1100000001 \
b1100000001 i
b10 -
b10 @
b10 G
b10 ]
0L
b11111111111111111111110011111111 j
b0 W
b0 Z
b0 g
1.
b101 D
b10011 ""
b100010011 ~
b100001000000000000100010011 y
b100001000000000000100010011 {
b10 A
1!
#90
0!
#95
b1100000000 U
b1100000000 l
b1100000000 m
b1100000000 k
b1100000000 q
0L
b0 #
b0 E
b0 K
b0 0"
b1100000000 V
b1100000000 \
b1100000000 i
b10 -
b10 @
b10 G
b10 ]
b11111111111111111111110100000000 j
b0 W
b0 Z
b0 g
1.
b0 )
b0 C
b0 I
b0 o
b100 R
b100 e
b100 r
0+
b100 D
x!"
x}
bx Q
bx a
bx w
bx #"
b101 A
b1100000001 n
b1 x
b1 z
b1 $"
bx ""
bx ~
bx y
bx {
1!
#100
0!
#105
b100 k
b1000 U
b1000 l
b1000 m
0!"
0}
b100001000000000000100010011 Q
b100001000000000000100010011 a
b100001000000000000100010011 w
b100001000000000000100010011 #"
1L
1$
b100 V
b100 \
b100 i
b1 -
b1 @
b1 G
b1 ]
b0 j
b100 W
b100 Z
b100 g
0.
b0 D
b0 x
b0 z
b0 $"
b10011 ""
b100010011 ~
b100001000000000000100010011 y
b100001000000000000100010011 {
b1100000000 M
b1100000000 c
b1100000000 ,"
b1100000000 /"
b1100000000 n
b100 A
1!
#110
0!
#115
1,
1%
1L
b0 j
b100 V
b100 \
b100 i
b1 -
b1 @
b1 G
b1 ]
0$
b1 D
b0 A
b1000 M
b1000 c
b1000 ,"
b1000 /"
b1000 n
1!
#120
0!
#125
b1000010 q
bx N
bx _
bx -"
b0 k
b1000 U
b1000 l
b1000 m
b10000100000000000010 p
b10 +"
b10 *"
b10 3
b0 V
b0 \
b0 i
b0 -
b0 @
b0 G
b0 ]
0,
0%
b10 D
0L
b1000 j
b1000 W
b1000 Z
b1000 g
b1000 R
b1000 e
b1000 r
b1000 T
b1000 d
b100001000000000000100010011 (
b100001000000000000100010011 2
b100001000000000000100010011 J
b100001000000000000100010011 S
b100001000000000000100010011 b
b1 A
1!
#130
0!
#135
0P
b1000010 q
b1 )
b1 C
b1 I
b1 o
b1000010 R
b1000010 e
b1000010 r
1+
b1000010 M
b1000010 c
b1000010 ,"
b1000010 /"
b1 #
b1 E
b1 K
b1 0"
b10 -
b10 @
b10 G
b10 ]
b0 W
b0 Z
b0 g
1.
b101 D
bx u
bx ("
b1000010 U
b1000010 l
b1000010 m
b1000010 k
1!"
b1111111111100000000000110010011 Q
b1111111111100000000000110010011 a
b1111111111100000000000110010011 w
b1111111111100000000000110010011 #"
b10 A
0L
b11111111111111111111111110111110 j
b1000010 V
b1000010 \
b1000010 i
bx `
bx s
bx %"
b10010011 ""
b110010011 ~
b1111111111100000000000110010011 y
b1111111111100000000000110010011 {
1!
#140
0!
#145
b1000010 q
0!"
b1000101011110000011 Q
b1000101011110000011 a
b1000101011110000011 w
b1000101011110000011 #"
b0 #
b0 E
b0 K
b0 0"
0L
b1000010 V
b1000010 \
b1000010 i
b10 -
b10 @
b10 G
b10 ]
b11111111111111111111111110111110 j
b0 W
b0 Z
b0 g
1.
b0 )
b0 C
b0 I
b0 o
b1000 R
b1000 e
b1000 r
0+
b100 D
b10 x
b10 z
b10 $"
b100 ""
b100 ~
b1000101011110000011 y
b1000101011110000011 {
b1000010 n
b101 A
1!
#150
0!
#155
b100 k
b1100 U
b1100 l
b1100 m
1$
0L
b100 V
b100 \
b100 i
b1 -
b1 @
b1 G
b1 ]
b100 j
b1000 W
b1000 Z
b1000 g
0.
b0 D
1!"
b1111111111100000000000110010011 Q
b1111111111100000000000110010011 a
b1111111111100000000000110010011 w
b1111111111100000000000110010011 #"
b100 A
b0 x
b0 z
b0 $"
b10010011 ""
b110010011 ~
b1111111111100000000000110010011 y
b1111111111100000000000110010011 {
1!
#160
0!
#165
b1000010 N
b1000010 _
b1000010 -"
1,
1%
0L
b100 j
b100 V
b100 \
b100 i
b1 -
b1 @
b1 G
b1 ]
0$
b1 D
b1100 M
b1100 c
b1100 ,"
b1100 /"
b1100 n
b0 A
1!
#170
0!
