multi-cycle/src/core/ControlUnit.v
module controlUnit(
    input clk,
    input reset,
    input [31:0] instr,
    output logic pcUpdate,
    output logic adrSrc,
    output logic memWrite,
    output logic [2:0] formatCtrl,
    output logic IRWrite,
    output logic regWrite,
    output logic [2:0] immSrc,
    output logic ALUSrcA,
    output logic [1:0] ALUSrcB,
    output logic invertOp,
    output logic [2:0] ALUCtrl,
    output logic [1:0] resSrc
);
    
    wire [6:0] funct7;
    wire [2:0] funct3; 
    wire [6:0] opcode;
    wire invertOp_t;

    assign funct7 = instr[31:25];
    assign funct3 = instr[14:12];
    assign opcode = instr[6:0];
    assign invertOp_t = funct7[5];

    
    localparam memFetch = 3'd0;
    localparam fetch = 3'd1;
    localparam decode = 3'd2;
    localparam execute_R = 3'd3;
    localparam writeBack_ALU = 3'd4;
    localparam execute_I = 3'd5;
    localparam memRead = 3'd6;
    localparam writeBack_mem = 3'd7;

    logic [2:0] currentState, nextState;

    //MAIN FSM
    //NEXT STATE LOGIC
    always_comb begin
        nextState = currentState; //Default Case
        case(currentState)
            memFetch: nextState = fetch;
            fetch: nextState = decode;
            decode: begin
                case(opcode)
                    7'b0110011: nextState = execute_R;
                    7'b0010011: nextState = execute_I;
                    7'b0000011: nextState = memRead;
                endcase
            end
            execute_R: nextState = writeBack_ALU;
            execute_I: nextState = writeBack_ALU;
            memRead: nextState = writeBack_mem;
            writeBack_mem: nextState = memFetch;
            writeBack_ALU: nextState = memFetch;
        endcase
    end

    //FSM REGISTER
    always_ff @(posedge clk) begin
        if(reset)
            currentState <= memFetch;
        else
            currentState <= nextState;
    end

    //OUTPUT LOGIC
    always_comb begin
        pcUpdate = 0;
        adrSrc = 0;
        memWrite = 0;
        formatCtrl = 3'b010;
        IRWrite = 0;
        regWrite = 0;
        immSrc = 3'd0;
        ALUSrcA = 0;
        ALUSrcB = 2'd0;
        invertOp = 0;
        resSrc = 2'd0;
        case(currentState)
            memFetch: begin
                pcUpdate = 1;
                ALUSrcA = 0;        //Setting ALU to calculate PC+4 here to support correct PC update after reset
                ALUSrcB = 2'd1;
                resSrc = 2'd0;
                IRWrite = 1;
            end
            fetch: begin
                //IRWrite = 1;
            end
            decode: begin
                ALUSrcA = 1;
                ALUSrcB = 2'd2;
                immSrc = 3'd0;
                resSrc = 2'd1;
                adrSrc = 1;
            end
            memRead: begin
                resSrc = 2'd0;
                adrSrc = 1;
                formatCtrl = funct3;
            end
            writeBack_mem: begin
                resSrc = 2'd2;
                regWrite = 1;
                ALUSrcA = 0;
                ALUSrcB = 2'd1;
                formatCtrl = funct3;
            end
            execute_R: begin
                ALUSrcA = 1;
                ALUSrcB = 2'd0;
                invertOp = invertOp_t;
            end
            execute_I: begin
                ALUSrcA = 1;
                ALUSrcB = 2'd2;
                immSrc = 3'd0;
                if(funct3 == 3'b101)
                    invertOp = invertOp_t;
            end
            writeBack_ALU: begin
                resSrc = 2'd0;
                regWrite = 1;
                ALUSrcA = 0;
                ALUSrcB = 2'd1;
            end
        endcase
    end

    //ALU DECODER
    always_comb begin
        ALUCtrl = 3'd0;
        case(currentState)
            memFetch: ALUCtrl = 3'b000;
            decode: ALUCtrl = 3'b000;
            execute_R: ALUCtrl = funct3;
            execute_I: ALUCtrl = funct3;
            writeBack_mem: ALUCtrl = 3'b000;
            writeBack_ALU: ALUCtrl = 3'b000;
        endcase
    end
endmodule

multi-cycle/src/blocks/ImmediateGenerator.v
module immediateGenerator(input [31:7] instr, input [2:0] immSrc, output reg [31:0] extendedImm);

    always @(*) begin
        extendedImm = 0;
        case(immSrc)
            3'b000: extendedImm = {{20{instr[31]}}, instr[31:20]}; //I Type
            3'b001: extendedImm = {{20{instr[31]}}, instr[31:25], instr[11:7]}; //S Type
            3'b010: extendedImm = {{20{instr[31]}}, instr[7], instr[30:25], instr[11:8], 1'b0}; //B Type
            3'b011: extendedImm = {instr[31:12], 12'b0}; //U type
            3'b100: extendedImm = {{11{instr[31]}}, instr[31], instr[20], instr[19:12], instr[30:21], 1'b0}; //J Type
            default: extendedImm = 32'b0;
        endcase
        //$display("%0d", extendedImm);
    end

endmodule

multi-cycle/src/blocks/ALU.v
module ALU(
    input [31:0] A,
    input [31:0] B,
    input invertOp,
    input [2:0] ALUCtrl,
    output reg [31:0] ALURes,
    output zero,
    output overflow
);
    wire [31:0] BEff;
    wire [31:0] resSub;
    assign BEff = (invertOp)? (~B + 1) : B;
    assign resSub = A-B;
    assign overflow = (A[31] != B[31]) && (resSub[31] != A[31]);
    assign zero = (resSub == 0);
    always @(*) begin
      case(ALUCtrl)
        3'b000: ALURes = A+BEff; //ADD/Sub
        3'b001: ALURes = A << B[4:0]; //SLL
        3'b010: ALURes = {31'b0, $signed(A) < $signed(B)}; //SLT
        3'b011: ALURes = A < B; //SLTU
        3'b100: ALURes = A ^ B; //XOR
        3'b101: ALURes = (!invertOp)? (A >> B[4:0]) : ($signed(A) >> B[4:0]); //SRL/SRA
        3'b110: ALURes = A | B;
        3'b111: ALURes = A & B;
      endcase
    end

endmodule

multi-cycle/src/utils/nMux.v
module nMux #(
    parameter N = 4
)(
    input [31:0] in [N-1:0],
    input [$clog2(N)-1:0] sel,
    output [31:0] out
);
    assign out = in[sel];
endmodule

multi-cycle/src/utils/Reg32.v
module reg32(
    input clk,
    input reset,
    input [31:0] in,
    output reg [31:0] out
);

    always @(posedge clk) begin
        if(reset)
            out <= 32'b0;
        else
            out <= in;
    end
endmodule

module enReg32(
    input clk,
    input reset,
    input enable,
    input [31:0] in,
    output reg [31:0] out
);
    always @(posedge clk) begin
        if(reset)
            out <= 32'b0;
        else if(enable)
            out <= in;
    end
endmodule

multi-cycle/src/blocks/Memory.v
module memory(
    input clk,
    input memWrite,
    input [2:0] formatCtrl,
    input [31:0] A1,
    input [31:0] WD,
    output reg [31:0] RD
);

    
    reg [31:0] mem [0:2047];
    reg [31:0] rawRead;
    reg [1:0] bytePos;

    //Synchronous Memory
    always @(posedge clk) begin
        rawRead <= mem[A1[12:2]];
        bytePos <= A1[1:0];
        if(memWrite)
            mem[A1[12:2]] <= WD;
    end

    loadFormatter lf(.dataIn(rawRead), .formatCtrl(formatCtrl), .bytePos(bytePos), .dataOut(RD));

    initial begin
        $readmemh("sim/program.hex", mem);
    end

    initial begin
        mem[32'h100 >> 2] = 32'hDEADBEEF;
        mem[32'h104 >> 2] = 32'hCAFEBABE;
        mem[32'h108 >> 2] = 32'h12345678;
        mem[32'h0FC >> 2] = 32'hAABBCCDD;
        mem[32'h200 >> 2] = 32'h11223344;
        mem[32'h204 >> 2] = 32'h55667788;
        mem[32'h208 >> 2] = 32'h99AABBCC;
    end
endmodule

module loadFormatter(
    input [31:0] dataIn,
    input [2:0] formatCtrl,
    input [1:0] bytePos,
    output reg [31:0] dataOut
);
    wire [7:0] byte_data;
    wire [15:0] half_data;
    assign byte_data = dataIn[bytePos*8 +: 8];
    assign half_data = dataIn[bytePos[1]*16 +: 16];
    wire byte_data_sign, half_data_sign;
    assign byte_data_sign = byte_data[7];
    assign half_data_sign = half_data[15];

    always_comb begin
        case(formatCtrl)
            3'b000: dataOut = {{24{byte_data_sign}}, byte_data}; //LB
            3'b001: dataOut = {{16{half_data_sign}}, half_data}; //LH
            3'b010: dataOut = dataIn; //LW
            3'b100: dataOut = {24'b0, byte_data}; //LBU
            3'b101: dataOut = {16'b0, half_data}; //LHU
            default: dataOut = dataIn;
        endcase
        //$display(bytePos, byte_start);
    end
endmodule

multi-cycle/src/blocks/RegisterFile.v
module registerFile(
    input clk,
    input reset,
    input regWrite,
    input [4:0] A1,
    input [4:0] A2,
    input [4:0] A3,
    input [31:0] WD,
    output [31:0] R1,
    output [31:0] R2
);

    reg [31:0] rFile [31:0];
    assign R1 = (A1 == 0)? 32'b0:rFile[A1];
    assign R2 = (A2 == 0)? 32'b0:rFile[A2];

    always @(posedge clk) begin
        if(reset) begin
            rFile[0] = 32'd0;
        end
        else if(regWrite && (A3 != 0)) begin
            rFile[A3] <= WD;
            $display("Write: x%0d = %0d (0x%h) time=%0t", A3, WD, WD, $time);
        end
    end

endmodule

multi-cycle/src/blocks/ProgramCounter.v
module programCounter(
    input clk,
    input reset,
    input pcUpdate,
    input [31:0] nextPC,
    output reg [31:0] currPC
);
    always @(posedge clk) begin
        if(reset)
            currPC <= 32'b0;
        else if(pcUpdate)
            currPC <= nextPC;
    end
endmodule

multi-cycle/src/core/datapath.v
module dataPath(
    input clk,
    input reset,
    input pcUpdate,
    input adrSrc,
    input memWrite,
    input [2:0] formatCtrl,
    input IRWrite,
    input regWrite,
    input [2:0] immSrc,
    input ALUSrcA,
    input [1:0] ALUSrcB,
    input invertOp,
    input [2:0] ALUCtrl,
    input [1:0] resSrc,
    output [31:0] instOut
);
    wire [31:0] currPC;
    wire [31:0] adrMuxIn [1:0];
    wire [31:0] memIn;
    wire [31:0] memRead;
    wire [31:0] instr;
    wire [31:0] reg1, reg2; // Register File Outputs
    wire [31:0] ALUSrcAMuxIn [1:0];
    wire [31:0] ALUSrcBMuxIn [3:0];
    wire [31:0] ALUA, ALUB;
    wire [31:0] ALURes;
    wire [31:0] resMuxIn [3:0];
    wire [31:0] result;
    wire zero, overflow;


    //Architectural State Elements
    programCounter PC(.clk(clk), .reset(reset), .pcUpdate(pcUpdate), .nextPC(result), .currPC(currPC));
    registerFile regFile(.clk(clk), .reset(reset), .regWrite(regWrite), .A1(instr[19:15]), .A2(instr[24:20]), .A3(instr[11:7]), .WD(result), .R1(reg1), .R2(reg2));
    memory mem(.clk(clk), .memWrite(memWrite), .formatCtrl(formatCtrl), .A1(memIn), .WD(), .RD(memRead));
    
    //Non Architectural State Elements
    enReg32 IRReg(.clk(clk), .reset(reset), .enable(IRWrite), .in(memRead), .out(instr));
    reg32 A(.clk(clk), .reset(reset), .in(reg1), .out(ALUSrcAMuxIn[1]));
    reg32 B(.clk(clk), .reset(reset), .in(reg2), .out(ALUSrcBMuxIn[0]));
    reg32 aluOut(.clk(clk), .reset(reset), .in(ALURes), .out(resMuxIn[0]));

    //Combinational Elements
    assign adrMuxIn[0] = currPC;
    assign adrMuxIn[1] = result;
    nMux #(.N(2)) adrMux(.in(adrMuxIn), .sel(adrSrc), .out(memIn));

    assign ALUSrcAMuxIn[0] = currPC;
    assign ALUSrcBMuxIn[1] = 32'd4;
    assign ALUSrcBMuxIn[3] = 32'd0;
    nMux #(.N(2)) ALUSrcAMux(.in(ALUSrcAMuxIn), .sel(ALUSrcA), .out(ALUA));
    nMux #(.N(4)) ALUSrcBMux(.in(ALUSrcBMuxIn), .sel(ALUSrcB), .out(ALUB));
    
    assign resMuxIn[1] = ALURes;
    assign resMuxIn[2] = memRead;
    assign resMuxIn[3] = 32'd0;
    nMux #(.N(4)) resMux(.in(resMuxIn), .sel(resSrc), .out(result));

    ALU alu(.A(ALUA), .B(ALUB), .invertOp(invertOp), .ALUCtrl(ALUCtrl), .ALURes(ALURes), .zero(zero), .overflow(overflow));
    immediateGenerator immGen(.instr(instr[31:7]), .immSrc(immSrc), .extendedImm(ALUSrcBMuxIn[2]));

    assign instOut = instr;
endmodule

multi-cycle/src/core/cpu.v
module CPU(
    input clk,
    input reset
);
    //Control Wires
    wire pcUpdate;
    wire adrSrc;
    wire memWrite;
    wire [2:0] formatCtrl;
    wire IRWrite;
    wire regWrite;
    wire [2:0] immSrc;
    wire ALUSrcA;
    wire [1:0] ALUSrcB;
    wire invertOp;
    wire [2:0] ALUCtrl;
    wire [1:0] resSrc;
    wire [31:0] instr;

    dataPath DP(
        .clk(clk),
        .reset(reset),
        .pcUpdate(pcUpdate),
        .adrSrc(adrSrc),
        .memWrite(memWrite),
        .formatCtrl(formatCtrl),
        .IRWrite(IRWrite),
        .regWrite(regWrite),
        .immSrc(immSrc),
        .ALUSrcA(ALUSrcA),
        .ALUSrcB(ALUSrcB),
        .invertOp(invertOp),
        .ALUCtrl(ALUCtrl),
        .resSrc(resSrc),
        .instOut(instr)
    );

    controlUnit CP(
        .clk(clk),
        .reset(reset),
        .instr(instr),
        .pcUpdate(pcUpdate),
        .adrSrc(adrSrc),
        .memWrite(memWrite),
        .formatCtrl(formatCtrl),
        .IRWrite(IRWrite),
        .regWrite(regWrite),
        .immSrc(immSrc),
        .ALUSrcA(ALUSrcA),
        .ALUSrcB(ALUSrcB),
        .invertOp(invertOp),
        .ALUCtrl(ALUCtrl),
        .resSrc(resSrc)
    );
endmodule

multi-cycle/sim/cpu_tb.v
`timescale 1ns/1ns

module cpu_tb();
    reg clk;
    reg reset;

    initial begin
        clk = 0;
        forever #5 clk = ~clk;
    end

    CPU DUT(.clk(clk), .reset(reset));
    initial begin
        $dumpfile("wave.vcd");
        $dumpvars(0, cpu_tb);
        reset = 1; #20
        reset = 0; #5000
        $finish;
    end
endmodule

multi-cycle/wave.vcd
$date
	Mon Jun  8 05:42:47 2026
$end
$version
	Icarus Verilog
$end
$timescale
	1ps
$end
$scope module cpu_tb $end
$var reg 1 ! clk $end
$var reg 1 " reset $end
$scope module DUT $end
$var wire 1 ! clk $end
$var wire 1 " reset $end
$var wire 2 # resSrc [1:0] $end
$var wire 1 $ regWrite $end
$var wire 1 % pcUpdate $end
$var wire 1 & memWrite $end
$var wire 1 ' invertOp $end
$var wire 32 ( instr [31:0] $end
$var wire 3 ) immSrc [2:0] $end
$var wire 3 * formatCtrl [2:0] $end
$var wire 1 + adrSrc $end
$var wire 1 , IRWrite $end
$var wire 2 - ALUSrcB [1:0] $end
$var wire 1 . ALUSrcA $end
$var wire 3 / ALUCtrl [2:0] $end
$scope module CP $end
$var wire 1 ! clk $end
$var wire 1 " reset $end
$var wire 7 0 opcode [6:0] $end
$var wire 1 1 invertOp_t $end
$var wire 32 2 instr [31:0] $end
$var wire 7 3 funct7 [6:0] $end
$var wire 3 4 funct3 [2:0] $end
$var parameter 3 5 decode $end
$var parameter 3 6 execute_I $end
$var parameter 3 7 execute_R $end
$var parameter 3 8 fetch $end
$var parameter 3 9 memFetch $end
$var parameter 3 : memRead $end
$var parameter 3 ; writeBack_ALU $end
$var parameter 3 < writeBack_mem $end
$var reg 3 = ALUCtrl [2:0] $end
$var reg 1 . ALUSrcA $end
$var reg 2 > ALUSrcB [1:0] $end
$var reg 1 , IRWrite $end
$var reg 1 + adrSrc $end
$var reg 3 ? currentState [2:0] $end
$var reg 3 @ formatCtrl [2:0] $end
$var reg 3 A immSrc [2:0] $end
$var reg 1 ' invertOp $end
$var reg 1 & memWrite $end
$var reg 3 B nextState [2:0] $end
$var reg 1 % pcUpdate $end
$var reg 1 $ regWrite $end
$var reg 2 C resSrc [1:0] $end
$upscope $end
$scope module DP $end
$var wire 3 D ALUCtrl [2:0] $end
$var wire 1 . ALUSrcA $end
$var wire 2 E ALUSrcB [1:0] $end
$var wire 1 , IRWrite $end
$var wire 1 + adrSrc $end
$var wire 1 ! clk $end
$var wire 3 F formatCtrl [2:0] $end
$var wire 3 G immSrc [2:0] $end
$var wire 32 H instOut [31:0] $end
$var wire 1 ' invertOp $end
$var wire 1 & memWrite $end
$var wire 1 % pcUpdate $end
$var wire 1 $ regWrite $end
$var wire 2 I resSrc [1:0] $end
$var wire 1 " reset $end
$var wire 1 J zero $end
$var wire 32 K result [31:0] $end
$var wire 32 L reg2 [31:0] $end
$var wire 32 M reg1 [31:0] $end
$var wire 1 N overflow $end
$var wire 32 O memRead [31:0] $end
$var wire 32 P memIn [31:0] $end
$var wire 32 Q instr [31:0] $end
$var wire 32 R currPC [31:0] $end
$var wire 32 S ALURes [31:0] $end
$var wire 32 T ALUB [31:0] $end
$var wire 32 U ALUA [31:0] $end
$scope module A $end
$var wire 1 ! clk $end
$var wire 1 " reset $end
$var wire 32 V in [31:0] $end
$var reg 32 W out [31:0] $end
$upscope $end
$scope module ALUSrcAMux $end
$var wire 32 X out [31:0] $end
$var wire 1 . sel $end
$var parameter 32 Y N $end
$upscope $end
$scope module ALUSrcBMux $end
$var wire 32 Z out [31:0] $end
$var wire 2 [ sel [1:0] $end
$var parameter 32 \ N $end
$upscope $end
$scope module B $end
$var wire 1 ! clk $end
$var wire 1 " reset $end
$var wire 32 ] in [31:0] $end
$var reg 32 ^ out [31:0] $end
$upscope $end
$scope module IRReg $end
$var wire 1 ! clk $end
$var wire 1 , enable $end
$var wire 1 " reset $end
$var wire 32 _ in [31:0] $end
$var reg 32 ` out [31:0] $end
$upscope $end
$scope module PC $end
$var wire 1 ! clk $end
$var wire 1 % pcUpdate $end
$var wire 1 " reset $end
$var wire 32 a nextPC [31:0] $end
$var reg 32 b currPC [31:0] $end
$upscope $end
$scope module adrMux $end
$var wire 32 c out [31:0] $end
$var wire 1 + sel $end
$var parameter 32 d N $end
$upscope $end
$scope module alu $end
$var wire 32 e A [31:0] $end
$var wire 3 f ALUCtrl [2:0] $end
$var wire 32 g B [31:0] $end
$var wire 1 ' invertOp $end
$var wire 1 N overflow $end
$var wire 1 J zero $end
$var wire 32 h resSub [31:0] $end
$var wire 32 i BEff [31:0] $end
$var reg 32 j ALURes [31:0] $end
$upscope $end
$scope module aluOut $end
$var wire 1 ! clk $end
$var wire 32 k in [31:0] $end
$var wire 1 " reset $end
$var reg 32 l out [31:0] $end
$upscope $end
$scope module immGen $end
$var wire 3 m immSrc [2:0] $end
$var wire 25 n instr [31:7] $end
$var reg 32 o extendedImm [31:0] $end
$upscope $end
$scope module mem $end
$var wire 32 p A1 [31:0] $end
$var wire 32 q WD [31:0] $end
$var wire 1 ! clk $end
$var wire 3 r formatCtrl [2:0] $end
$var wire 1 & memWrite $end
$var wire 32 s RD [31:0] $end
$var reg 2 t bytePos [1:0] $end
$var reg 32 u rawRead [31:0] $end
$scope module lf $end
$var wire 2 v bytePos [1:0] $end
$var wire 32 w dataIn [31:0] $end
$var wire 3 x formatCtrl [2:0] $end
$var wire 1 y half_data_sign $end
$var wire 16 z half_data [15:0] $end
$var wire 1 { byte_data_sign $end
$var wire 8 | byte_data [7:0] $end
$var reg 32 } dataOut [31:0] $end
$upscope $end
$upscope $end
$scope module regFile $end
$var wire 5 ~ A1 [4:0] $end
$var wire 5 !" A2 [4:0] $end
$var wire 5 "" A3 [4:0] $end
$var wire 1 ! clk $end
$var wire 1 $ regWrite $end
$var wire 1 " reset $end
$var wire 32 #" WD [31:0] $end
$var wire 32 $" R2 [31:0] $end
$var wire 32 %" R1 [31:0] $end
$upscope $end
$scope module resMux $end
$var wire 32 &" out [31:0] $end
$var wire 2 '" sel [1:0] $end
$var parameter 32 (" N $end
$upscope $end
$upscope $end
$upscope $end
$upscope $end
$enddefinitions $end
$comment Show the parameter values. $end
$dumpall
b100 ("
b10 d
b100 \
b10 Y
b111 <
b100 ;
b110 :
b0 9
b1 8
b11 7
b101 6
b10 5
$end
#0
$dumpvars
b0 '"
bx &"
bx %"
bx $"
bx #"
bx ""
bx !"
bx ~
bx }
bx |
x{
bx z
xy
b10 x
bx w
bx v
bx u
bx t
bx s
b10 r
bz q
bx p
bx o
bx n
b0 m
bx l
bx k
bx j
bx i
bx h
bx g
b0 f
bx e
bx c
bx b
bx a
bx `
bx _
bx ^
bx ]
b0 [
bx Z
bx X
bx W
bx V
bx U
bx T
bx S
bx R
bx Q
bx P
bx O
xN
bx M
bx L
bx K
xJ
b0 I
bx H
b0 G
b10 F
b0 E
b0 D
b0 C
bx B
b0 A
b10 @
bx ?
b0 >
b0 =
bx 4
bx 3
bx 2
x1
bx 0
b0 /
0.
b0 -
0,
0+
b10 *
b0 )
bx (
0'
0&
0%
0$
b0 #
1"
0!
$end
#5000
0N
b0 o
b0 L
b0 ]
b0 $"
b0 M
b0 V
b0 %"
01
b0 n
b0 ""
b0 !"
b0 ~
b0 0
b0 4
b0 3
b100 S
b100 j
b100 k
b100 i
1,
b1 -
b1 >
b1 E
b1 [
1%
b1 B
0J
b11111111111111111111111111111100 h
b0 U
b0 X
b0 e
b0 P
b0 c
b0 p
b0 R
b0 b
b0 (
b0 2
b0 H
b0 Q
b0 `
b0 W
b100 T
b100 Z
b100 g
b0 ^
b0 K
b0 a
b0 #"
b0 &"
b0 l
b0 ?
1!
#10000
0!
#15000
0y
1{
b10010011 z
b10000000000000000000010010011 O
b10000000000000000000010010011 _
b10000000000000000000010010011 s
b10000000000000000000010010011 }
b10010011 |
b0 t
b0 v
b10000000000000000000010010011 u
b10000000000000000000010010011 w
1!
#20000
0!
0"
#25000
b100000000 o
b0 S
b0 j
b0 k
b0 i
b1000000000000000000001 n
b1 ""
b10011 0
b1000 3
1J
b0 h
b0 T
b0 Z
b0 g
b0 -
b0 >
b0 E
b0 [
0,
0%
b10 B
b10000000000000000000010010011 (
b10000000000000000000010010011 2
b10000000000000000000010010011 H
b10000000000000000000010010011 Q
b10000000000000000000010010011 `
b100 K
b100 a
b100 #"
b100 &"
b100 l
b1 ?
1!
#30000
0!
#35000
b100000000 P
b100000000 c
b100000000 p
b100000000 S
b100000000 j
b100000000 k
b100000000 i
1+
b1 #
b1 C
b1 I
b1 '"
0J
b11111111111111111111111100000000 h
b100000000 T
b100000000 Z
b100000000 g
b10 -
b10 >
b10 E
b10 [
1.
b101 B
b10 ?
b100000000 K
b100000000 a
b100000000 #"
b100000000 &"
b0 l
1!
#40000
0!
#45000
1y
b11011110101011011011111011101111 O
b11011110101011011011111011101111 _
b11011110101011011011111011101111 s
b11011110101011011011111011101111 }
b0 #
b0 C
b0 I
b0 '"
0J
b11111111111111111111111100000000 h
b100000000 T
b100000000 Z
b100000000 g
b10 -
b10 >
b10 E
b10 [
1.
b0 P
b0 c
b0 p
0+
b100 B
b11101111 |
b1011111011101111 z
b11011110101011011011111011101111 u
b11011110101011011011111011101111 w
b100000000 l
b101 ?
1!
#50000
0!
#55000
b100 S
b100 j
b100 k
b100 i
1$
0J
b11111111111111111111111111111100 h
b100 T
b100 Z
b100 g
b1 -
b1 >
b1 E
b1 [
0.
b0 B
0y
b10000000000000000000010010011 O
b10000000000000000000010010011 _
b10000000000000000000010010011 s
b10000000000000000000010010011 }
b100 ?
b10010011 |
b10010011 z
b10000000000000000000010010011 u
b10000000000000000000010010011 w
1!
#60000
0!
#65000
1,
1%
0J
b11111111111111111111111111111100 h
b100 T
b100 Z
b100 g
b1 -
b1 >
b1 E
b1 [
0$
b1 B
b100 K
b100 a
b100 #"
b100 &"
b100 l
b0 ?
1!
#70000
0!
#75000
b0 i
b0 T
b0 Z
b0 g
b0 -
b0 >
b0 E
b0 [
0,
0%
b10 B
b100 S
b100 j
b100 k
b1 ?
0J
b100 h
b100 U
b100 X
b100 e
b100 P
b100 c
b100 p
b100 R
b100 b
1!
#80000
0!
#85000
b100000000 i
b100000000 P
b100000000 c
b100000000 p
b100000000 K
b100000000 a
b100000000 #"
b100000000 &"
b100000000 S
b100000000 j
b100000000 k
0{
1y
b1010010100000011 O
b1010010100000011 _
b1010010100000011 s
b1010010100000011 }
1+
b1 #
b1 C
b1 I
b1 '"
b100000000 T
b100000000 Z
b100000000 g
b10 -
b10 >
b10 E
b10 [
0J
b11111111111111111111111100000000 h
b0 U
b0 X
b0 e
1.
b101 B
b11 |
b1010010100000011 z
b1010010100000011 u
b1010010100000011 w
b10 ?
1!
#90000
0!
#95000
0J
b0 #
b0 C
b0 I
b0 '"
b100000000 T
b100000000 Z
b100000000 g
b10 -
b10 >
b10 E
b10 [
b11111111111111111111111100000000 h
b0 U
b0 X
b0 e
1.
b100 P
b100 c
b100 p
0+
b100 B
1{
b11011110101011011011111011101111 O
b11011110101011011011111011101111 _
b11011110101011011011111011101111 s
b11011110101011011011111011101111 }
b101 ?
b100000000 l
b11101111 |
b1011111011101111 z
b11011110101011011011111011101111 u
b11011110101011011011111011101111 w
1!
#100000
0!
#105000
b100 i
b1000 S
b1000 j
b1000 k
0{
b1010010100000011 O
b1010010100000011 _
b1010010100000011 s
b1010010100000011 }
1J
1$
b100 T
b100 Z
b100 g
b1 -
b1 >
b1 E
b1 [
b0 h
b100 U
b100 X
b100 e
0.
b0 B
b11 |
b1010010100000011 z
b1010010100000011 u
b1010010100000011 w
b100 ?
1!
#110000
0!
#115000
1,
1%
1J
b0 h
b100 T
b100 Z
b100 g
b1 -
b1 >
b1 E
b1 [
0$
b1 B
b0 ?
b1000 K
b1000 a
b1000 #"
b1000 &"
b1000 l
1!
#120000
0!
#125000
b0 o
b100000000 M
b100000000 V
b100000000 %"
b0 i
b1000 S
b1000 j
b1000 k
b101001010 n
b1010 ""
b1 ~
b11 0
b10 4
b0 3
b0 T
b0 Z
b0 g
b0 -
b0 >
b0 E
b0 [
0,
0%
b10 B
0J
b1000 h
b1000 U
b1000 X
b1000 e
b1000 P
b1000 c
b1000 p
b1000 R
b1000 b
b1010010100000011 (
b1010010100000011 2
b1010010100000011 H
b1010010100000011 Q
b1010010100000011 `
b1 ?
1!
#130000
0!
#135000
b100000000 P
b100000000 c
b100000000 p
b100000000 K
b100000000 a
b100000000 #"
b100000000 &"
b100000000 S
b100000000 j
b100000000 k
1+
b1 #
b1 C
b1 I
b1 '"
b10 -
b10 >
b10 E
b10 [
b100000000 h
b100000000 U
b100000000 X
b100000000 e
1.
b110 B
1{
b1000010110000011 O
b1000010110000011 _
b1000010110000011 s
b1000010110000011 }
b10 ?
b100000000 W
b10000011 |
b1000010110000011 z
b1000010110000011 u
b1000010110000011 w
1!
#140000
0!
#145000
b1000 S
b1000 j
b1000 k
b11011110101011011011111011101111 O
b11011110101011011011111011101111 _
b11011110101011011011111011101111 s
b11011110101011011011111011101111 }
b0 #
b0 C
b0 I
b0 '"
b0 -
b0 >
b0 E
b0 [
b1000 h
b1000 U
b1000 X
b1000 e
0.
b100000000 P
b100000000 c
b100000000 p
1+
b111 B
b11101111 |
b1011111011101111 z
b11011110101011011011111011101111 u
b11011110101011011011111011101111 w
b100000000 l
b110 ?
1!
#150000
0!
#155000
b1100 S
b1100 j
b1100 k
b100 i
b100 h
b100 T
b100 Z
b100 g
b1 -
b1 >
b1 E
b1 [
1$
b10 #
b10 C
b10 I
b10 '"
0+
b0 B
b111 ?
b1000 P
b1000 c
b1000 p
b11011110101011011011111011101111 K
b11011110101011011011111011101111 a
b11011110101011011011111011101111 #"
b11011110101011011011111011101111 &"
b1000 l
1!
#160000
0!
#165000
b1000010110000011 O
b1000010110000011 _
b1000010110000011 s
b1000010110000011 }
1,
1%
b1100 K
b1100 a
b1100 #"
b1100 &"
b0 #
b0 C
b0 I
b0 '"
b100 h
b100 T
b100 Z
b100 g
b1 -
b1 >
b1 E
b1 [
0$
b1 B
b10000011 |
b1000010110000011 z
b1000010110000011 u
b1000010110000011 w
b1100 l
b0 ?
1!
#170000
0!
#175000
b0 i
b0 T
b0 Z
b0 g
b0 -
b0 >
b0 E
b0 [
0,
0%
b10 B
b100001011 n
b1011 ""
b0 4
b1100 S
b1100 j
b1100 k
b1 ?
b1000010110000011 (
b1000010110000011 2
b1000010110000011 H
b1000010110000011 Q
b1000010110000011 `
b1100 h
b1100 U
b1100 X
b1100 e
b1100 P
b1100 c
b1100 p
b1100 R
b1100 b
1!
#180000
0!
#185000
b100000000 P
b100000000 c
b100000000 p
b100000000 K
b100000000 a
b100000000 #"
b100000000 &"
b100000000 S
b100000000 j
b100000000 k
0{
b100001000011000000011 O
b100001000011000000011 _
b100001000011000000011 s
b100001000011000000011 }
1+
b1 #
b1 C
b1 I
b1 '"
b10 -
b10 >
b10 E
b10 [
b100000000 h
b100000000 U
b100000000 X
b100000000 e
1.
b110 B
b11 |
b1000011000000011 z
b100001000011000000011 u
b100001000011000000011 w
b10 ?
1!
#190000
0!
#195000
b1100 S
b1100 j
b1100 k
b0 *
b0 @
b0 F
b0 r
b0 x
b0 #
b0 C
b0 I
b0 '"
b0 -
b0 >
b0 E
b0 [
b1100 h
b1100 U
b1100 X
b1100 e
0.
b100000000 P
b100000000 c
b100000000 p
1+
b111 B
1{
b11111111111111111111111111101111 O
b11111111111111111111111111101111 _
b11111111111111111111111111101111 s
b11111111111111111111111111101111 }
b110 ?
b100000000 l
b11101111 |
b1011111011101111 z
b11011110101011011011111011101111 u
b11011110101011011011111011101111 w
1!
#200000
0!
#205000
b10000 S
b10000 j
b10000 k
b100 i
b1000 h
b100 T
b100 Z
b100 g
b1 -
b1 >
b1 E
b1 [
1$
b10 #
b10 C
b10 I
b10 '"
b0 *
b0 @
b0 F
b0 r
b0 x
0+
b0 B
b1100 P
b1100 c
b1100 p
b11111111111111111111111111101111 K
b11111111111111111111111111101111 a
b11111111111111111111111111101111 #"
b11111111111111111111111111101111 &"
b1100 l
b111 ?
1!
#210000
0!
#215000
1,
1%
b0 #
b0 C
b0 I
b0 '"
b1000 h
b100 T
b100 Z
b100 g
b1 -
b1 >
b1 E
b1 [
0$
b10 *
b10 @
b10 F
b10 r
b10 x
b1 B
0{
b10000 K
b10000 a
b10000 #"
b10000 &"
b100001000011000000011 O
b100001000011000000011 _
b100001000011000000011 s
b100001000011000000011 }
b0 ?
b10000 l
b11 |
b1000011000000011 z
b100001000011000000011 u
b100001000011000000011 w
1!
#220000
0!
#225000
b1 o
b100000000 L
b100000000 ]
b100000000 $"
b0 i
b10000 S
b10000 j
b10000 k
b10000100001100 n
b1100 ""
b1 !"
b0 T
b0 Z
b0 g
b0 -
b0 >
b0 E
b0 [
0,
0%
b10 B
b10000 h
b10000 U
b10000 X
b10000 e
b10000 P
b10000 c
b10000 p
b10000 R
b10000 b
b100001000011000000011 (
b100001000011000000011 2
b100001000011000000011 H
b100001000011000000011 Q
b100001000011000000011 `
b1 ?
1!
#230000
0!
