multi-cycle/src/core/ControlUnit.v
module controlUnit(
    input clk,
    input reset,
    input [31:0] instr,
    input zero,
    input overflow,
    input negative,
    input borrow,
    output logic pcUpdate,
    output logic adrSrc,
    output logic memWrite,
    output logic [2:0] formatCtrl,
    output logic IRWrite,
    output logic regWrite,
    output logic [2:0] immSrc,
    output logic [1:0] ALUSrcA,
    output logic [1:0] ALUSrcB,
    output logic invertOp,
    output logic [2:0] ALUCtrl,
    output logic [1:0] resSrc
);
    
    wire [6:0] funct7;
    wire [2:0] funct3; 
    wire [6:0] opcode;
    wire invertOp_t;

    assign funct7 = instr[31:25];
    assign funct3 = instr[14:12];
    assign opcode = instr[6:0];
    assign invertOp_t = funct7[5];

    
    localparam memFetch = 4'd0;
    localparam fetch = 4'd1;
    localparam decode = 4'd2;
    localparam execute_R = 4'd3;
    localparam writeBack_ALU = 4'd4;
    localparam execute_I = 4'd5;
    localparam memRead = 4'd6;
    localparam writeBack_mem = 4'd7;
    localparam memStore = 4'd8;
    localparam pcSet = 4'd9;
    localparam branch = 4'd10;

    logic [3:0] currentState, nextState;

    //MAIN FSM
    //NEXT STATE LOGIC
    always_comb begin
        nextState = currentState; //Default Case
        case(currentState)
            memFetch: nextState = fetch;
            fetch: nextState = decode;
            decode: begin
                case(opcode)
                    7'b0110011: nextState = execute_R;
                    7'b0010011: nextState = execute_I;
                    7'b0000011: nextState = memRead;
                    7'b0100011: nextState = memStore;
                    7'b1100011: nextState = branch;
                endcase
            end
            execute_R: nextState = writeBack_ALU;
            execute_I: nextState = writeBack_ALU;
            memRead: nextState = writeBack_mem;
            memStore: nextState = pcSet;
            branch: nextState = pcSet;
            pcSet: nextState = memFetch;
            writeBack_mem: nextState = memFetch;
            writeBack_ALU: nextState = memFetch;
        endcase
    end

    //FSM REGISTER
    always_ff @(posedge clk) begin
        if(reset)
            currentState <= memFetch;
        else
            currentState <= nextState;
    end

    //OUTPUT LOGIC
    always_comb begin
        pcUpdate = 0;
        adrSrc = 0;
        memWrite = 0;
        formatCtrl = 3'b010;
        IRWrite = 0;
        regWrite = 0;
        immSrc = 3'd0;
        ALUSrcA = 2'd0;
        ALUSrcB = 2'd0;
        invertOp = 0;
        resSrc = 2'd0;
        case(currentState)
            memFetch: begin
                adrSrc = 0;
                pcUpdate = 1;
                ALUSrcA = 2'd0;        //Setting ALU to calculate PC+4 here to support correct PC update after reset
                ALUSrcB = 2'd1;
                resSrc = 2'd0;
                IRWrite = 1;
            end
            fetch: begin
                //IRWrite = 1;
            end
            decode: begin
                if(opcode != 7'b1100011)
                    ALUSrcA = 2'd1;
                else
                    ALUSrcA = 2'd2;
                ALUSrcB = 2'd2;
                resSrc = 2'd1;
                adrSrc = 1;
                case(opcode)
                    7'b0010011: immSrc = 3'b000;
                    7'b0000011: immSrc = 3'b000;
                    7'b0100011: immSrc = 3'b001;
                    7'b1100011: immSrc = 3'b010;
                endcase
            end
            memRead: begin
                resSrc = 2'd0;
                adrSrc = 1;
                formatCtrl = funct3;
            end
            memStore: begin
                resSrc = 2'd0;
                adrSrc = 1;
                memWrite = 1;
                formatCtrl = funct3;
            end
            branch: begin
                ALUSrcA = 2'd1;
                ALUSrcB = 2'd0;
                invertOp = 1;
                case(funct3)
                    3'b000: pcUpdate = zero; //BEQ
                    3'b001: pcUpdate = !zero;//BNE
                    3'b100: pcUpdate = (negative^overflow);//BLT
                    3'b101: pcUpdate = !(negative^overflow);//BGE
                    3'b110: pcUpdate = borrow;//BLTU
                    3'b111: pcUpdate = !borrow;//BGEU
                endcase
            end
            pcSet: begin
                ALUSrcA = 2'd0;
                ALUSrcB = 2'd1;
            end
            writeBack_mem: begin
                resSrc = 2'd2;
                regWrite = 1;
                ALUSrcA = 2'd0;
                ALUSrcB = 2'd1;
                formatCtrl = funct3;
            end
            execute_R: begin
                ALUSrcA = 2'd1;
                ALUSrcB = 2'd0;
                invertOp = invertOp_t;
            end
            execute_I: begin
                ALUSrcA = 2'd1;
                ALUSrcB = 2'd2;
                immSrc = 3'd0;
                if(funct3 == 3'b101)
                    invertOp = invertOp_t;
            end
            writeBack_ALU: begin
                resSrc = 2'd0;
                regWrite = 1;
                ALUSrcA = 2'd0;
                ALUSrcB = 2'd1;
            end
        endcase
    end

    //ALU DECODER
    always_comb begin
        ALUCtrl = 3'd0;
        case(currentState)
            memFetch: ALUCtrl = 3'b000;
            decode: ALUCtrl = 3'b000;
            memStore: ALUCtrl = 3'b000;
            branch: ALUCtrl = 3'b000;
            pcSet: ALUCtrl = 3'b000;
            execute_R: ALUCtrl = funct3;
            execute_I: ALUCtrl = funct3;
            writeBack_mem: ALUCtrl = 3'b000;
            writeBack_ALU: ALUCtrl = 3'b000;
        endcase
    end
endmodule

multi-cycle/src/blocks/ImmediateGenerator.v
module immediateGenerator(input [31:7] instr, input [2:0] immSrc, output reg [31:0] extendedImm);

    always @(*) begin
        extendedImm = 0;
        case(immSrc)
            3'b000: extendedImm = {{20{instr[31]}}, instr[31:20]}; //I Type
            3'b001: extendedImm = {{20{instr[31]}}, instr[31:25], instr[11:7]}; //S Type
            3'b010: extendedImm = {{20{instr[31]}}, instr[7], instr[30:25], instr[11:8], 1'b0}; //B Type
            3'b011: extendedImm = {instr[31:12], 12'b0}; //U type
            3'b100: extendedImm = {{11{instr[31]}}, instr[31], instr[20], instr[19:12], instr[30:21], 1'b0}; //J Type
            default: extendedImm = 32'b0;
        endcase
        //$display("%0d", extendedImm);
    end

endmodule

multi-cycle/src/blocks/ALU.v
module ALU(
    input [31:0] A,
    input [31:0] B,
    input invertOp,
    input [2:0] ALUCtrl,
    output reg [31:0] ALURes,
    output zero,
    output overflow,
    output negative,
    output borrow
);
    wire [31:0] BEff;
    wire [31:0] resSub;
    assign BEff = (invertOp)? (~B + 1) : B;
    
    assign resSub = A-B;
    assign overflow = (A[31] != B[31]) && (resSub[31] != A[31]);
    assign zero = (resSub == 0);
    assign negative = resSub[31];
    assign borrow = A < B;

    always @(*) begin
      case(ALUCtrl)
        3'b000: ALURes = A+BEff; //ADD/Sub
        3'b001: ALURes = A << B[4:0]; //SLL
        3'b010: ALURes = {31'b0, $signed(A) < $signed(B)}; //SLT
        3'b011: ALURes = A < B; //SLTU
        3'b100: ALURes = A ^ B; //XOR
        3'b101: begin
          if(invertOp)
            ALURes = $signed(A) >>> B[4:0]; //SRA
          else
            ALURes = A >> B[4:0]; //SRL
        end
        3'b110: ALURes = A | B;
        3'b111: ALURes = A & B;
      endcase
    end


endmodule

multi-cycle/src/utils/nMux.v
module nMux #(
    parameter N = 4
)(
    input [31:0] in [N-1:0],
    input [$clog2(N)-1:0] sel,
    output [31:0] out
);
    assign out = in[sel];
endmodule

multi-cycle/src/utils/Reg32.v
module reg32(
    input clk,
    input reset,
    input [31:0] in,
    output reg [31:0] out
);

    always @(posedge clk) begin
        if(reset)
            out <= 32'b0;
        else
            out <= in;
    end
endmodule

module enReg32(
    input clk,
    input reset,
    input enable,
    input [31:0] in,
    output reg [31:0] out
);
    always @(posedge clk) begin
        if(reset)
            out <= 32'b0;
        else if(enable)
            out <= in;
    end
endmodule

multi-cycle/src/blocks/Memory.v
module memory(
    input clk,
    input memWrite,
    input [2:0] formatCtrl,
    input [31:0] A1,
    input [31:0] WD,
    output reg [31:0] RD
);

    
    reg [31:0] mem [0:2047];
    reg [31:0] rawRead;
    reg [1:0] bytePos;
    wire [3:0] byteMask;
    wire [31:0] fWrite;

    //Synchronous Memory
    always @(posedge clk) begin
        rawRead <= mem[A1[12:2]];
        bytePos <= A1[1:0];
        if(memWrite) begin
            if(byteMask[0])
                mem[A1[12:2]][7:0] <= fWrite[7:0];
            if(byteMask[1])
                mem[A1[12:2]][15:8] <= fWrite[15:8];
            if(byteMask[2])
                mem[A1[12:2]][23:16] <= fWrite[23:16];
            if(byteMask[3])
                mem[A1[12:2]][31:24] <= fWrite[31:24];
            
            //$display("MEM WRITE: addr=%h data=%h" , A1, fWrite);
        end
    end

    loadFormatter lf(.dataIn(rawRead), .formatCtrl(formatCtrl), .bytePos(bytePos), .dataOut(RD));
    storeFormatter sf(.dataIn(WD), .formatCtrl(formatCtrl), .bytePos(bytePos), .byteMask(byteMask), .dataOut(fWrite));

    initial begin
        $readmemh("sim/program.hex", mem);
    end

endmodule

module loadFormatter(
    input [31:0] dataIn,
    input [2:0] formatCtrl,
    input [1:0] bytePos,
    output reg [31:0] dataOut
);
    wire [7:0] byte_data;
    wire [15:0] half_data;
    assign byte_data = dataIn[bytePos*8 +: 8];
    assign half_data = dataIn[bytePos[1]*16 +: 16];
    wire byte_data_sign, half_data_sign;
    assign byte_data_sign = byte_data[7];
    assign half_data_sign = half_data[15];

    always_comb begin
        case(formatCtrl)
            3'b000: dataOut = {{24{byte_data_sign}}, byte_data}; //LB
            3'b001: dataOut = {{16{half_data_sign}}, half_data}; //LH
            3'b010: dataOut = dataIn; //LW
            3'b100: dataOut = {24'b0, byte_data}; //LBU
            3'b101: dataOut = {16'b0, half_data}; //LHU
            default: dataOut = dataIn;
        endcase
        //$display(bytePos, byte_start);
    end
endmodule

module storeFormatter(
    input [31:0] dataIn,
    input [2:0] formatCtrl,
    input [1:0] bytePos,
    output reg [3:0] byteMask,
    output reg [31:0] dataOut
);
    always @(*) begin
        case(formatCtrl)
            3'b000: begin //SB
                dataOut = dataIn << 8*bytePos;
                byteMask = 4'b0001 << bytePos;
            end
            3'b001: begin //SH
                dataOut = dataIn << 16*bytePos[1];
                byteMask = 4'b0011 << 2*bytePos[1];
            end
            3'b010: begin //SW
                dataOut = dataIn;
                byteMask = 4'b1111;
            end
        endcase
    end
endmodule

multi-cycle/src/blocks/RegisterFile.v
module registerFile(
    input clk,
    input reset,
    input regWrite,
    input [4:0] A1,
    input [4:0] A2,
    input [4:0] A3,
    input [31:0] WD,
    output [31:0] R1,
    output [31:0] R2
);

    reg [31:0] rFile [31:0];
    assign R1 = (A1 == 0)? 32'b0:rFile[A1];
    assign R2 = (A2 == 0)? 32'b0:rFile[A2];

    always @(posedge clk) begin
        if(reset) begin
            rFile[0] = 32'd0;
        end
        else if(regWrite && (A3 != 0)) begin
            rFile[A3] <= WD;
            $display("Write: x%0d = %0d (0x%h) time=%0t", A3, WD, WD, $time);
        end
    end

endmodule

multi-cycle/src/blocks/ProgramCounter.v
module programCounter(
    input clk,
    input reset,
    input pcUpdate,
    input [31:0] nextPC,
    output reg [31:0] currPC
);
    always @(posedge clk) begin
        if(reset)
            currPC <= 32'b0;
        else if(pcUpdate)
            currPC <= nextPC;
    end
endmodule

multi-cycle/src/core/datapath.v
module dataPath(
    input clk,
    input reset,
    input pcUpdate,
    input adrSrc,
    input memWrite,
    input [2:0] formatCtrl,
    input IRWrite,
    input regWrite,
    input [2:0] immSrc,
    input [1:0] ALUSrcA,
    input [1:0] ALUSrcB,
    input invertOp,
    input [2:0] ALUCtrl,
    input [1:0] resSrc,
    output [31:0] instOut,
    output zero,
    output overflow,
    output negative,
    output borrow
);
    wire [31:0] currPC;
    wire [31:0] adrMuxIn [1:0];
    wire [31:0] memIn;
    wire [31:0] memRead;
    wire [31:0] instr;
    wire [31:0] reg1, reg2; // Register File Outputs
    wire [31:0] ALUSrcAMuxIn [3:0];
    wire [31:0] ALUSrcBMuxIn [3:0];
    wire [31:0] ALUA, ALUB;
    wire [31:0] ALURes;
    wire [31:0] resMuxIn [3:0];
    wire [31:0] result;


    //Architectural State Elements
    programCounter PC(.clk(clk), .reset(reset), .pcUpdate(pcUpdate), .nextPC(result), .currPC(currPC));
    registerFile regFile(.clk(clk), .reset(reset), .regWrite(regWrite), .A1(instr[19:15]), .A2(instr[24:20]), .A3(instr[11:7]), .WD(result), .R1(reg1), .R2(reg2));
    memory mem(.clk(clk), .memWrite(memWrite), .formatCtrl(formatCtrl), .A1(memIn), .WD(ALUSrcBMuxIn[0]), .RD(memRead));
    
    //Non Architectural State Elements
    enReg32 oldPC(.clk(clk), .reset(reset), .enable(IRWrite), .in(currPC), .out(ALUSrcAMuxIn[2]));
    enReg32 IRReg(.clk(clk), .reset(reset), .enable(IRWrite), .in(memRead), .out(instr));
    reg32 A(.clk(clk), .reset(reset), .in(reg1), .out(ALUSrcAMuxIn[1]));
    reg32 B(.clk(clk), .reset(reset), .in(reg2), .out(ALUSrcBMuxIn[0]));
    reg32 aluOut(.clk(clk), .reset(reset), .in(ALURes), .out(resMuxIn[0]));

    //Combinational Elements
    assign adrMuxIn[0] = currPC;
    assign adrMuxIn[1] = result;
    nMux #(.N(2)) adrMux(.in(adrMuxIn), .sel(adrSrc), .out(memIn));

    assign ALUSrcAMuxIn[0] = currPC;
    assign ALUSrcAMuxIn[3] = 32'd0;
    assign ALUSrcBMuxIn[1] = 32'd4;
    assign ALUSrcBMuxIn[3] = 32'd0;
    nMux #(.N(4)) ALUSrcAMux(.in(ALUSrcAMuxIn), .sel(ALUSrcA), .out(ALUA));
    nMux #(.N(4)) ALUSrcBMux(.in(ALUSrcBMuxIn), .sel(ALUSrcB), .out(ALUB));
    
    assign resMuxIn[1] = ALURes;
    assign resMuxIn[2] = memRead;
    assign resMuxIn[3] = 32'd0;
    nMux #(.N(4)) resMux(.in(resMuxIn), .sel(resSrc), .out(result));

    ALU alu(.A(ALUA), .B(ALUB), .invertOp(invertOp), .ALUCtrl(ALUCtrl), .ALURes(ALURes), .zero(zero), .overflow(overflow), .negative(negative), .borrow(borrow));
    immediateGenerator immGen(.instr(instr[31:7]), .immSrc(immSrc), .extendedImm(ALUSrcBMuxIn[2]));

    assign instOut = instr;
endmodule

multi-cycle/src/core/cpu.v
module CPU(
    input clk,
    input reset
);
    //Control Wires
    wire pcUpdate;
    wire adrSrc;
    wire memWrite;
    wire [2:0] formatCtrl;
    wire IRWrite;
    wire regWrite;
    wire [2:0] immSrc;
    wire [1:0] ALUSrcA;
    wire [1:0] ALUSrcB;
    wire invertOp;
    wire [2:0] ALUCtrl;
    wire [1:0] resSrc;
    wire [31:0] instr;
    wire zero, overflow, negative, borrow;

    dataPath DP(
        .clk(clk),
        .reset(reset),
        .pcUpdate(pcUpdate),
        .adrSrc(adrSrc),
        .memWrite(memWrite),
        .formatCtrl(formatCtrl),
        .IRWrite(IRWrite),
        .regWrite(regWrite),
        .immSrc(immSrc),
        .ALUSrcA(ALUSrcA),
        .ALUSrcB(ALUSrcB),
        .invertOp(invertOp),
        .ALUCtrl(ALUCtrl),
        .resSrc(resSrc),
        .instOut(instr),
        .zero(zero),
        .overflow(overflow),
        .negative(negative),
        .borrow(borrow)
    );

    controlUnit CP(
        .clk(clk),
        .reset(reset),
        .instr(instr),
        .zero(zero),
        .overflow(overflow),
        .negative(negative),
        .borrow(borrow),
        .pcUpdate(pcUpdate),
        .adrSrc(adrSrc),
        .memWrite(memWrite),
        .formatCtrl(formatCtrl),
        .IRWrite(IRWrite),
        .regWrite(regWrite),
        .immSrc(immSrc),
        .ALUSrcA(ALUSrcA),
        .ALUSrcB(ALUSrcB),
        .invertOp(invertOp),
        .ALUCtrl(ALUCtrl),
        .resSrc(resSrc)
    );
endmodule

multi-cycle/sim/cpu_tb.v
`timescale 1ns/1ns

module cpu_tb();
    reg clk;
    reg reset;

    initial begin
        clk = 0;
        forever #5 clk = ~clk;
    end

    CPU DUT(.clk(clk), .reset(reset));
    initial begin
        $dumpfile("wave.vcd");
        $dumpvars(0, cpu_tb);
        reset = 1; #20
        reset = 0; #5000
        $finish;
    end
endmodule

multi-cycle/wave.vcd
$date
	Tue Jun  9 03:28:27 2026
$end
$version
	Icarus Verilog
$end
$timescale
	1ns
$end
$scope module cpu_tb $end
$var reg 1 ! clk $end
$var reg 1 " reset $end
$scope module DUT $end
$var wire 1 ! clk $end
$var wire 1 " reset $end
$var wire 1 # zero $end
$var wire 2 $ resSrc [1:0] $end
$var wire 1 % regWrite $end
$var wire 1 & pcUpdate $end
$var wire 1 ' overflow $end
$var wire 1 ( negative $end
$var wire 1 ) memWrite $end
$var wire 1 * invertOp $end
$var wire 32 + instr [31:0] $end
$var wire 3 , immSrc [2:0] $end
$var wire 3 - formatCtrl [2:0] $end
$var wire 1 . borrow $end
$var wire 1 / adrSrc $end
$var wire 1 0 IRWrite $end
$var wire 2 1 ALUSrcB [1:0] $end
$var wire 2 2 ALUSrcA [1:0] $end
$var wire 3 3 ALUCtrl [2:0] $end
$scope module CP $end
$var wire 1 ! clk $end
$var wire 1 " reset $end
$var wire 1 # zero $end
$var wire 1 ' overflow $end
$var wire 7 4 opcode [6:0] $end
$var wire 1 ( negative $end
$var wire 1 5 invertOp_t $end
$var wire 32 6 instr [31:0] $end
$var wire 7 7 funct7 [6:0] $end
$var wire 3 8 funct3 [2:0] $end
$var wire 1 . borrow $end
$var parameter 4 9 branch $end
$var parameter 4 : decode $end
$var parameter 4 ; execute_I $end
$var parameter 4 < execute_R $end
$var parameter 4 = fetch $end
$var parameter 4 > memFetch $end
$var parameter 4 ? memRead $end
$var parameter 4 @ memStore $end
$var parameter 4 A pcSet $end
$var parameter 4 B writeBack_ALU $end
$var parameter 4 C writeBack_mem $end
$var reg 3 D ALUCtrl [2:0] $end
$var reg 2 E ALUSrcA [1:0] $end
$var reg 2 F ALUSrcB [1:0] $end
$var reg 1 0 IRWrite $end
$var reg 1 / adrSrc $end
$var reg 4 G currentState [3:0] $end
$var reg 3 H formatCtrl [2:0] $end
$var reg 3 I immSrc [2:0] $end
$var reg 1 * invertOp $end
$var reg 1 ) memWrite $end
$var reg 4 J nextState [3:0] $end
$var reg 1 & pcUpdate $end
$var reg 1 % regWrite $end
$var reg 2 K resSrc [1:0] $end
$upscope $end
$scope module DP $end
$var wire 3 L ALUCtrl [2:0] $end
$var wire 2 M ALUSrcA [1:0] $end
$var wire 2 N ALUSrcB [1:0] $end
$var wire 1 0 IRWrite $end
$var wire 1 / adrSrc $end
$var wire 1 ! clk $end
$var wire 3 O formatCtrl [2:0] $end
$var wire 3 P immSrc [2:0] $end
$var wire 32 Q instOut [31:0] $end
$var wire 1 * invertOp $end
$var wire 1 ) memWrite $end
$var wire 1 & pcUpdate $end
$var wire 1 % regWrite $end
$var wire 2 R resSrc [1:0] $end
$var wire 1 " reset $end
$var wire 1 # zero $end
$var wire 32 S result [31:0] $end
$var wire 32 T reg2 [31:0] $end
$var wire 32 U reg1 [31:0] $end
$var wire 1 ' overflow $end
$var wire 1 ( negative $end
$var wire 32 V memRead [31:0] $end
$var wire 32 W memIn [31:0] $end
$var wire 32 X instr [31:0] $end
$var wire 32 Y currPC [31:0] $end
$var wire 1 . borrow $end
$var wire 32 Z ALURes [31:0] $end
$var wire 32 [ ALUB [31:0] $end
$var wire 32 \ ALUA [31:0] $end
$scope module A $end
$var wire 1 ! clk $end
$var wire 1 " reset $end
$var wire 32 ] in [31:0] $end
$var reg 32 ^ out [31:0] $end
$upscope $end
$scope module ALUSrcAMux $end
$var wire 32 _ out [31:0] $end
$var wire 2 ` sel [1:0] $end
$var parameter 32 a N $end
$upscope $end
$scope module ALUSrcBMux $end
$var wire 32 b out [31:0] $end
$var wire 2 c sel [1:0] $end
$var parameter 32 d N $end
$upscope $end
$scope module B $end
$var wire 1 ! clk $end
$var wire 1 " reset $end
$var wire 32 e in [31:0] $end
$var reg 32 f out [31:0] $end
$upscope $end
$scope module IRReg $end
$var wire 1 ! clk $end
$var wire 1 0 enable $end
$var wire 1 " reset $end
$var wire 32 g in [31:0] $end
$var reg 32 h out [31:0] $end
$upscope $end
$scope module PC $end
$var wire 1 ! clk $end
$var wire 1 & pcUpdate $end
$var wire 1 " reset $end
$var wire 32 i nextPC [31:0] $end
$var reg 32 j currPC [31:0] $end
$upscope $end
$scope module adrMux $end
$var wire 32 k out [31:0] $end
$var wire 1 / sel $end
$var parameter 32 l N $end
$upscope $end
$scope module alu $end
$var wire 32 m A [31:0] $end
$var wire 3 n ALUCtrl [2:0] $end
$var wire 32 o B [31:0] $end
$var wire 1 * invertOp $end
$var wire 1 ' overflow $end
$var wire 1 # zero $end
$var wire 32 p resSub [31:0] $end
$var wire 1 ( negative $end
$var wire 1 . borrow $end
$var wire 32 q BEff [31:0] $end
$var reg 32 r ALURes [31:0] $end
$upscope $end
$scope module aluOut $end
$var wire 1 ! clk $end
$var wire 32 s in [31:0] $end
$var wire 1 " reset $end
$var reg 32 t out [31:0] $end
$upscope $end
$scope module immGen $end
$var wire 3 u immSrc [2:0] $end
$var wire 25 v instr [31:7] $end
$var reg 32 w extendedImm [31:0] $end
$upscope $end
$scope module mem $end
$var wire 32 x A1 [31:0] $end
$var wire 32 y WD [31:0] $end
$var wire 1 ! clk $end
$var wire 3 z formatCtrl [2:0] $end
$var wire 1 ) memWrite $end
$var wire 32 { fWrite [31:0] $end
$var wire 4 | byteMask [3:0] $end
$var wire 32 } RD [31:0] $end
$var reg 2 ~ bytePos [1:0] $end
$var reg 32 !" rawRead [31:0] $end
$scope module lf $end
$var wire 2 "" bytePos [1:0] $end
$var wire 32 #" dataIn [31:0] $end
$var wire 3 $" formatCtrl [2:0] $end
$var wire 1 %" half_data_sign $end
$var wire 16 &" half_data [15:0] $end
$var wire 1 '" byte_data_sign $end
$var wire 8 (" byte_data [7:0] $end
$var reg 32 )" dataOut [31:0] $end
$upscope $end
$scope module sf $end
$var wire 2 *" bytePos [1:0] $end
$var wire 32 +" dataIn [31:0] $end
$var wire 3 ," formatCtrl [2:0] $end
$var reg 4 -" byteMask [3:0] $end
$var reg 32 ." dataOut [31:0] $end
$upscope $end
$upscope $end
$scope module oldPC $end
$var wire 1 ! clk $end
$var wire 1 0 enable $end
$var wire 32 /" in [31:0] $end
$var wire 1 " reset $end
$var reg 32 0" out [31:0] $end
$upscope $end
$scope module regFile $end
$var wire 5 1" A1 [4:0] $end
$var wire 5 2" A2 [4:0] $end
$var wire 5 3" A3 [4:0] $end
$var wire 1 ! clk $end
$var wire 1 % regWrite $end
$var wire 1 " reset $end
$var wire 32 4" WD [31:0] $end
$var wire 32 5" R2 [31:0] $end
$var wire 32 6" R1 [31:0] $end
$upscope $end
$scope module resMux $end
$var wire 32 7" out [31:0] $end
$var wire 2 8" sel [1:0] $end
$var parameter 32 9" N $end
$upscope $end
$upscope $end
$upscope $end
$upscope $end
$enddefinitions $end
$comment Show the parameter values. $end
$dumpall
b100 9"
b10 l
b100 d
b100 a
b111 C
b100 B
b1001 A
b1000 @
b110 ?
b0 >
b1 =
b11 <
b101 ;
b10 :
b1010 9
$end
#0
$dumpvars
b0 8"
bx 7"
bx 6"
bx 5"
bx 4"
bx 3"
bx 2"
bx 1"
bx 0"
bx /"
bx ."
b1111 -"
b10 ,"
bx +"
bx *"
bx )"
bx ("
x'"
bx &"
x%"
b10 $"
bx #"
bx ""
bx !"
bx ~
bx }
b1111 |
bx {
b10 z
bx y
bx x
bx w
bx v
b0 u
bx t
bx s
bx r
bx q
bx p
bx o
b0 n
bx m
bx k
bx j
bx i
bx h
bx g
bx f
bx e
b0 c
bx b
b0 `
bx _
bx ^
bx ]
bx \
bx [
bx Z
bx Y
bx X
bx W
bx V
bx U
bx T
bx S
b0 R
bx Q
b0 P
b10 O
b0 N
b0 M
b0 L
b0 K
bx J
b0 I
b10 H
bx G
b0 F
b0 E
b0 D
bx 8
bx 7
bx 6
x5
bx 4
b0 3
b0 2
b0 1
00
0/
x.
b10 -
b0 ,
bx +
0*
0)
x(
x'
0&
0%
b0 $
x#
1"
0!
$end
#5
0'
b0 w
b0 T
b0 e
b0 5"
b0 U
b0 ]
b0 6"
05
1(
b0 v
b0 3"
b0 2"
b0 1"
b0 4
b0 8
b0 7
b0 {
b0 ."
b100 Z
b100 r
b100 s
b100 q
10
b1 1
b1 F
b1 N
b1 c
1&
b1 J
0#
b11111111111111111111111111111100 p
1.
b0 \
b0 _
b0 m
b0 W
b0 k
b0 x
b0 Y
b0 j
b0 /"
b0 0"
b0 +
b0 6
b0 Q
b0 X
b0 h
b0 ^
b100 [
b100 b
b100 o
b0 f
b0 y
b0 +"
b0 S
b0 i
b0 4"
b0 7"
b0 t
b0 G
1!
#10
0!
#15
0%"
1'"
b10010011 &"
b101000000000000010010011 V
b101000000000000010010011 g
b101000000000000010010011 }
b101000000000000010010011 )"
b10010011 ("
b0 ~
b0 ""
b0 *"
b101000000000000010010011 !"
b101000000000000010010011 #"
1!
#20
0!
0"
#25
b1010 w
bx T
bx e
bx 5"
b0 Z
b0 r
b0 s
b0 q
0(
b10100000000000001 v
b1 3"
b1010 2"
b10011 4
1#
b0 p
0.
b0 [
b0 b
b0 o
b0 1
b0 F
b0 N
b0 c
00
0&
b10 J
b101000000000000010010011 +
b101000000000000010010011 6
b101000000000000010010011 Q
b101000000000000010010011 X
b101000000000000010010011 h
b100 S
b100 i
b100 4"
b100 7"
b100 t
b1 G
1!
#30
0!
#35
b101 J
bx {
bx ."
b1010 W
b1010 k
b1010 x
b1010 Z
b1010 r
b1010 s
b1010 q
1(
1/
b1 $
b1 K
b1 R
b1 8"
b10 1
b10 F
b10 N
b10 c
b1 2
b1 E
b1 M
b1 `
b10 G
b1010 S
b1010 i
b1010 4"
b1010 7"
b0 t
0#
b11111111111111111111111111110110 p
1.
b1010 [
b1010 b
b1010 o
bx f
bx y
bx +"
1!
#40
0!
#45
0'"
b11100000000000110010011 V
b11100000000000110010011 g
b11100000000000110010011 }
b11100000000000110010011 )"
b0 $
b0 K
b0 R
b0 8"
0#
b11111111111111111111111111110110 p
1.
b1010 [
b1010 b
b1010 o
b10 1
b10 F
b10 N
b10 c
b1 2
b1 E
b1 M
b1 `
b0 W
b0 k
b0 x
0/
b100 J
b1110000 ("
b10 ~
b10 ""
b10 *"
b1110000 &"
b11100000000000110010011 !"
b11100000000000110010011 #"
b1010 t
b101 G
1!
#50
0!
#55
b100 Z
b100 r
b100 s
b100 q
1%
0#
b11111111111111111111111111111100 p
1.
b100 [
b100 b
b100 o
b1 1
b1 F
b1 N
b1 c
b0 2
b0 E
b0 M
b0 `
b0 J
1'"
b101000000000000010010011 V
b101000000000000010010011 g
b101000000000000010010011 }
b101000000000000010010011 )"
b100 G
b0 ~
b0 ""
b0 *"
b10010011 ("
b10010011 &"
b101000000000000010010011 !"
b101000000000000010010011 #"
1!
#60
0!
#65
10
1&
0#
b11111111111111111111111111111100 p
1.
b100 [
b100 b
b100 o
b1 1
b1 F
b1 N
b1 c
0%
b1 J
b100 S
b100 i
b100 4"
b100 7"
b100 t
b0 G
1!
#70
0!
#75
x'
bx q
b10 J
bx Z
bx r
bx s
x(
bx [
bx b
bx o
b0 1
b0 F
b0 N
b0 c
00
0&
b1 G
x#
bx p
x.
b100 \
b100 _
b100 m
b100 W
b100 k
b100 x
b100 Y
b100 j
b100 /"
1!
#80
0!
#85
0'
b1010 Z
b1010 r
b1010 s
b1010 q
1(
0'"
b101000000000000100010011 V
b101000000000000100010011 g
b101000000000000100010011 }
b101000000000000100010011 )"
b1010 W
b1010 k
b1010 x
1/
b1 $
b1 K
b1 R
b1 8"
0#
b11111111111111111111111111110110 p
1.
b1010 [
b1010 b
b1010 o
b10 1
b10 F
b10 N
b10 c
b0 \
b0 _
b0 m
b1 2
b1 E
b1 M
b1 `
b101 J
b10011 ("
b100010011 &"
b101000000000000100010011 !"
b101000000000000100010011 #"
b1010 S
b1010 i
b1010 4"
b1010 7"
bx t
b10 G
1!
#90
0!
#95
b0 $
b0 K
b0 R
b0 8"
0#
1.
b1010 [
b1010 b
b1010 o
b10 1
b10 F
b10 N
b10 c
b11111111111111111111111111110110 p
b0 \
b0 _
b0 m
b1 2
b1 E
b1 M
b1 `
b100 W
b100 k
b100 x
0/
b100 J
b11100000000000110010011 V
b11100000000000110010011 g
b11100000000000110010011 }
b11100000000000110010011 )"
b101 G
b1010 t
b10 ~
b10 ""
b10 *"
b1110000 ("
b1110000 &"
b11100000000000110010011 !"
b11100000000000110010011 #"
1!
#100
0!
#105
b100 q
0(
b1000 Z
b1000 r
b1000 s
b101000000000000100010011 V
b101000000000000100010011 g
b101000000000000100010011 }
b101000000000000100010011 )"
1%
1#
0.
b100 [
b100 b
b100 o
b1 1
b1 F
b1 N
b1 c
b0 p
b100 \
b100 _
b100 m
b0 2
b0 E
b0 M
b0 `
b0 J
b0 ~
b0 ""
b0 *"
b10011 ("
b100010011 &"
b101000000000000100010011 !"
b101000000000000100010011 #"
b100 G
1!
#110
0!
#115
10
1&
1#
b0 p
0.
b100 [
b100 b
b100 o
b1 1
b1 F
b1 N
b1 c
0%
b1 J
b0 G
b1000 S
b1000 i
b1000 4"
b1000 7"
b1000 t
1!
#120
0!
#125
x'
b1010 w
bx q
x(
bx Z
bx r
bx s
b10100000000000010 v
b10 3"
x.
bx [
bx b
bx o
b0 1
b0 F
b0 N
b0 c
00
0&
b10 J
x#
bx p
b1000 \
b1000 _
b1000 m
b1000 W
b1000 k
b1000 x
b1000 Y
b1000 j
b1000 /"
b100 0"
b101000000000000100010011 +
b101000000000000100010011 6
b101000000000000100010011 Q
b101000000000000100010011 X
b101000000000000100010011 h
b1 G
1!
#130
0!
#135
0'
b1010 Z
b1010 r
b1010 s
b1010 q
1(
b1010 W
b1010 k
b1010 x
1/
b1 $
b1 K
b1 R
b1 8"
0#
b11111111111111111111111111110110 p
1.
b1010 [
b1010 b
b1010 o
b10 1
b10 F
b10 N
b10 c
b0 \
b0 _
b0 m
b1 2
b1 E
b1 M
b1 `
b101 J
1'"
b11100000000000110010011 V
b11100000000000110010011 g
b11100000000000110010011 }
b11100000000000110010011 )"
b10 G
b1010 S
b1010 i
b1010 4"
b1010 7"
bx t
b10010011 ("
b110010011 &"
b11100000000000110010011 !"
b11100000000000110010011 #"
1!
#140
0!
